{
  "visitedSites": 192000,
  "monitoredSites": 73831,
  "prebidSites": 35387,
  "versionDistribution": {
    "v9.40.0": 34,
    "v9.40.0-pre": 274,
    "v9.39.0": 85,
    "v9.38.0": 10,
    "v9.37.0": 51,
    "v9.37.0-pre": 5,
    "v9.36.0": 34,
    "v9.35.0": 41,
    "v9.34.0": 24,
    "v9.33.0": 95,
    "v9.32.0": 806,
    "v9.32.0-pre": 7,
    "v9.31.0": 58,
    "v9.31.0-pre": 486,
    "v9.30.0": 2483,
    "v9.30.0-pre": 39,
    "v9.29.0": 370,
    "v9.28.0": 2097,
    "v9.28.0-pre": 107,
    "v9.27.0": 179,
    "v9.26.0": 4948,
    "v9.25.0": 708,
    "v9.25.0-MBA": 1,
    "v9.24.0": 612,
    "v9.24.0-pre": 8,
    "v9.23.0": 3296,
    "v9.23.0-pre": 33,
    "v9.22.0": 4156,
    "v9.21.0": 77,
    "v9.20.0": 106,
    "v9.19.0": 310,
    "v9.19.0-pre": 144,
    "v9.18.0": 381,
    "v9.18.0-pre": 18,
    "v9.17.0": 151,
    "v9.16.0": 232,
    "v9.16.0-pre": 9,
    "v9.15.0": 203,
    "v9.15.0-pre": 1,
    "v9.14.0": 492,
    "v9.13.0": 4171,
    "v9.12.0": 428,
    "v9.12.0-pre": 48,
    "v9.11.0": 737,
    "v9.10.0": 48,
    "v9.10.0-pre": 2,
    "v9.9.0": 55,
    "v9.8.0": 6,
    "v9.8.0-pre": 4,
    "v9.7.0": 7,
    "v9.6.0": 712,
    "v9.5.0": 392,
    "v9.4.1": 27,
    "v9.4.0": 6,
    "v9.3.0": 4,
    "v9.3.0-pre": 315,
    "v9.2.0": 214,
    "v9.1.0": 20,
    "v9.0.0": 4,
    "v8.52.9": 14,
    "v8.52.8": 124,
    "v8.52.5": 5,
    "v8.52.2": 756,
    "v8.52.2-internal": 4,
    "v8.52.1": 535,
    "v8.52.0": 883,
    "v8.52.0-pre": 2,
    "v8.51.0": 279,
    "v8.50.0": 974,
    "v8.49.0": 652,
    "v8.48.0": 32,
    "v8.48.0-pre": 2,
    "v8.47.0": 325,
    "v8.46.0": 1859,
    "v8.46.0-pre": 7,
    "v8.45.0": 131,
    "v8.44.0": 59,
    "v8.43.0": 12,
    "v8.42.0": 46,
    "v8.41.0": 7,
    "v8.40.0": 37,
    "v8.39.0": 18,
    "v8.39.0-pre": 29,
    "v8.38.0": 99,
    "v8.37.0": 71,
    "v8.36.0": 57,
    "v8.35.0": 21,
    "v8.34.0": 25,
    "v8.33.0": 3,
    "v8.32.0": 41,
    "v8.32.0-pre": 71,
    "v8.31.0": 124,
    "v8.31.0-pre": 13,
    "v8.30.0": 140,
    "v8.30.0-pre": 1,
    "v8.29.0": 4,
    "v8.28.0": 24,
    "v8.27.0": 510,
    "v8.26.0": 39,
    "v8.26.0-mol-1": 1,
    "v8.25.0": 8,
    "v8.24.0": 31,
    "v8.23.0": 15,
    "v8.23.0-pre": 11,
    "v8.22.0": 34,
    "v8.21.0": 7,
    "v8.20.0": 445,
    "v8.19.0": 90,
    "v8.19.0-pre": 5,
    "v8.18.0": 85,
    "v8.17.0": 45,
    "v8.16.0": 4,
    "v8.15.0": 1,
    "v8.14.0": 100,
    "v8.13.0": 13,
    "v8.13.0-pre": 1,
    "v8.12.0": 32,
    "v8.11.0": 8,
    "v8.10.0": 5,
    "v8.9.0": 4,
    "v8.8.0": 76,
    "v8.7.0": 10,
    "v8.6.0": 22,
    "v8.6.0-pre": 3,
    "v8.5.0": 10,
    "v8.4.0": 1,
    "v8.3.0": 50,
    "v8.2.0": 76,
    "v7.54.5": 32,
    "v7.54.5-fa": 1,
    "v7.54.4": 13,
    "v7.54.3": 47,
    "v7.54.2": 6,
    "v7.54.1": 112,
    "v7.54.1-pre": 11,
    "v7.54.0": 6,
    "v7.53.0": 2,
    "v7.52.0": 5,
    "v7.51.0": 1,
    "v7.50.0": 36,
    "v7.50.0-pre": 2,
    "v7.49.0": 7,
    "v7.48.0": 27,
    "v7.47.0": 143,
    "v7.47.0-pre": 4,
    "v7.46.0": 1,
    "v7.46.0-pre": 2,
    "v7.45.0": 61,
    "v7.44.0": 28,
    "v7.43.0": 8,
    "v7.42.0": 10,
    "v7.42.0-pre": 2,
    "v7.41.0": 9,
    "v7.40.0": 4,
    "v7.39.0": 410,
    "v7.37.0": 3,
    "v7.36.0-pre": 1,
    "v7.35.0": 98,
    "v7.34.0": 4,
    "v7.33.0": 4,
    "v7.30.0": 13,
    "v7.29.0": 1,
    "v7.25.0": 11,
    "v7.24.0": 3,
    "v7.23.1": 1,
    "v7.22.0": 66,
    "v7.18.0": 4,
    "v7.17.0": 1,
    "v7.16.0": 1,
    "v7.15.0": 3,
    "v7.13.0-pre": 61,
    "v7.12.0": 3,
    "v7.11.0-pre": 1,
    "v7.10.0": 2,
    "v7.9.0": 1,
    "v7.8.0": 1,
    "v7.7.0": 1,
    "v7.6.0": 1,
    "v7.5.0": 9,
    "v7.4.0": 1,
    "v7.3.0": 2,
    "v7.2.0": 4,
    "v7.1.0": 3,
    "v6.29.3": 28,
    "v6.29.1": 21,
    "v6.29.0": 2,
    "v6.27.0": 83,
    "v6.25.1-c": 1,
    "v6.25.0": 5,
    "v6.24.1": 4,
    "v6.23.0": 1,
    "v6.22.0-pre": 1,
    "v6.21.1": 1,
    "v6.20.0": 2,
    "v6.19.0": 1,
    "v6.18.0": 1485,
    "v6.17.0": 4,
    "v6.16.0": 1,
    "v6.15.0": 1,
    "v6.15.0-pre": 4,
    "v6.14.0": 1,
    "v6.13.0": 3,
    "v6.12.0": 7,
    "v6.10.0-pre": 30,
    "v6.9.0": 2,
    "v6.8.0": 4,
    "v6.7.0": 1,
    "v6.6.0": 31,
    "v6.5.0": 15,
    "v6.4.0": 7,
    "v6.3.0": 1,
    "v6.2.0": 2,
    "v6.0.0": 12,
    "v5.20.3": 113,
    "v5.20.0": 4,
    "v5.18.0": 1,
    "v5.14.0": 1,
    "v5.13.0": 2,
    "v5.11.0": 1,
    "v5.10.0": 1,
    "v5.7.0": 1,
    "v5.1.0": 2,
    "v4.43.4": 9,
    "v4.43.2": 1,
    "v4.43.1": 1,
    "v4.43.0": 28,
    "v4.40.0": 1,
    "v4.39.0": 2,
    "v4.37.0": 1,
    "v2.9.0": 3,
    "v9.35": 14
  },
  "moduleDistribution": {
    "userId": 39864,
    "rubiconBidAdapter": 31407,
    "schain": 30214,
    "id5IdSystem": 28088,
    "sharedIdSystem": 27725,
    "pubmaticBidAdapter": 27717,
    "appnexusBidAdapter": 27229,
    "consentManagementUsp": 26628,
    "criteoIdSystem": 26475,
    "rtdModule": 24305,
    "ixBidAdapter": 23731,
    "priceFloors": 23170,
    "tripleliftBidAdapter": 22870,
    "criteoBidAdapter": 22350,
    "unifiedIdSystem": 22135,
    "currency": 21528,
    "identityLinkIdSystem": 20940,
    "openxBidAdapter": 20690,
    "consentManagementTcf": 20423,
    "gptPreAuction": 19167,
    "33acrossIdSystem": 17219,
    "prebidServerBidAdapter": 16353,
    "fpdModule": 15594,
    "sharethroughBidAdapter": 15559,
    "pairIdSystem": 15490,
    "lotamePanoramaIdSystem": 15267,
    "liveIntentIdSystem": 15007,
    "adagioBidAdapter": 14888,
    "topicsFpdModule": 14883,
    "teadsBidAdapter": 14781,
    "consentManagementGpp": 13806,
    "gumgumBidAdapter": 13598,
    "sovrnBidAdapter": 13294,
    "dfpAdServerVideo": 12899,
    "rtbhouseBidAdapter": 12049,
    "onetagBidAdapter": 12042,
    "uid2IdSystem_shared": 11820,
    "uid2IdSystem": 11686,
    "paapi": 11501,
    "amxBidAdapter": 11067,
    "pubProvidedIdSystem": 11010,
    "smartadserverBidAdapter": 10884,
    "adagioRtdProvider": 10792,
    "unrulyBidAdapter": 10643,
    "seedtagBidAdapter": 10631,
    "consentManagement": 10158,
    "ttdBidAdapter": 10051,
    "medianetBidAdapter": 9787,
    "smilewantedBidAdapter": 9017,
    "33acrossBidAdapter": 8868,
    "paapiForGpt": 8868,
    "richaudienceBidAdapter": 8850,
    "adfBidAdapter": 8452,
    "improvedigitalBidAdapter": 8446,
    "kargoBidAdapter": 8445,
    "vidazooBidAdapter": 8153,
    "kueezRtbBidAdapter": 7948,
    "oguryBidAdapter": 7854,
    "undertoneBidAdapter": 7785,
    "gridBidAdapter": 7765,
    "connectIdSystem": 7666,
    "riseBidAdapter": 7260,
    "adyoulikeBidAdapter": 7253,
    "nativoBidAdapter": 7132,
    "concertBidAdapter": 6750,
    "amxIdSystem": 6654,
    "tcfControl": 6633,
    "conversantBidAdapter": 6540,
    "allowActivities": 6539,
    "adagioAnalyticsAdapter": 6519,
    "quantcastIdSystem": 6395,
    "sonobiBidAdapter": 6093,
    "yahooAdsBidAdapter": 5943,
    "fabrickIdSystem": 5788,
    "sizeMappingV2": 5703,
    "hadronIdSystem": 5627,
    "ozoneBidAdapter": 5579,
    "atsAnalyticsAdapter": 5381,
    "justpremiumBidAdapter": 5280,
    "genericAnalyticsAdapter": 5277,
    "contxtfulRtdProvider": 5020,
    "minutemediaBidAdapter": 5006,
    "merkleIdSystem": 4981,
    "adtelligentBidAdapter": 4960,
    "sizeMapping": 4842,
    "yieldmoBidAdapter": 4826,
    "lmpIdSystem": 4792,
    "pubmaticIHAnalyticsAdapter": 4748,
    "jwplayerRtdProvider": 4742,
    "ftrackIdSystem": 4687,
    "roxotAnalyticsAdapter": 4683,
    "outbrainBidAdapter": 4655,
    "gdprEnforcement": 4472,
    "linkedInAdsIdSystem": 4161,
    "eplanningBidAdapter": 4119,
    "insticatorBidAdapter": 4061,
    "smaatoBidAdapter": 3833,
    "nextMillenniumBidAdapter": 3682,
    "adpod": 3601,
    "adkernelBidAdapter": 3528,
    "sirdataRtdProvider": 3516,
    "themoneytizerBidAdapter": 3515,
    "nativeRendering": 3493,
    "invibesBidAdapter": 3168,
    "colossussspBidAdapter": 3129,
    "s2sTesting": 3096,
    "pulsepointBidAdapter": 3064,
    "missenaBidAdapter": 3064,
    "moneytizerBidAdapter": 3063,
    "optidigitalBidAdapter": 2948,
    "gppControl_usnat": 2934,
    "resetdigitalBidAdapter": 2916,
    "hadronRtdProvider": 2874,
    "videoModule": 2858,
    "connectadBidAdapter": 2847,
    "luponmediaBidAdapter": 2805,
    "betweenBidAdapter": 2684,
    "freewheel-sspBidAdapter": 2619,
    "gppControl_usstates": 2578,
    "pgamsspBidAdapter": 2555,
    "intentIqIdSystem": 2542,
    "pubxaiAnalyticsAdapter": 2482,
    "sparteoBidAdapter": 2480,
    "videojsVideoProvider": 2480,
    "euidIdSystem": 2476,
    "taboolaBidAdapter": 2404,
    "nobidBidAdapter": 2358,
    "publinkIdSystem": 2344,
    "fledgeForGpt": 2335,
    "enrichmentFpdModule": 2284,
    "adponeBidAdapter": 2253,
    "revcontentBidAdapter": 2201,
    "zeta_global_sspBidAdapter": 2147,
    "compassBidAdapter": 2139,
    "aidemBidAdapter": 2112,
    "waardexBidAdapter": 2035,
    "automatadAnalyticsAdapter": 2025,
    "liveIntentAnalyticsAdapter": 2024,
    "admaticBidAdapter": 1853,
    "vidoomyBidAdapter": 1712,
    "intentIqAnalyticsAdapter": 1680,
    "magniteAnalyticsAdapter": 1654,
    "teadsIdSystem": 1645,
    "adtargetBidAdapter": 1643,
    "permutiveRtdProvider": 1584,
    "timeoutRtdProvider": 1527,
    "anPspParamsConverter": 1525,
    "cadentApertureMXBidAdapter": 1503,
    "debugging": 1499,
    "videoheroesBidAdapter": 1478,
    "bidViewability": 1474,
    "apacdexBidAdapter": 1468,
    "mgidBidAdapter": 1441,
    "yandexBidAdapter": 1441,
    "admixerBidAdapter": 1439,
    "id5AnalyticsAdapter": 1434,
    "airgridRtdProvider": 1426,
    "sspBCBidAdapter": 1410,
    "imdsBidAdapter": 1361,
    "rhythmoneBidAdapter": 1345,
    "visxBidAdapter": 1314,
    "adheseBidAdapter": 1291,
    "omsBidAdapter": 1287,
    "nexx360BidAdapter": 1287,
    "pubmaticAnalyticsAdapter": 1275,
    "iasRtdProvider": 1254,
    "mediagoBidAdapter": 1226,
    "mediafuseBidAdapter": 1178,
    "instreamTracking": 1172,
    "yieldoneBidAdapter": 1170,
    "unicornBidAdapter": 1154,
    "pubxaiRtdProvider": 1151,
    "azerionedgeRtdProvider": 1146,
    "dgkeywordRtdProvider": 1107,
    "imRtdProvider": 1091,
    "setupadBidAdapter": 1090,
    "showheroes-bsBidAdapter": 1086,
    "justIdSystem": 1073,
    "sublimeBidAdapter": 1073,
    "fluctBidAdapter": 1072,
    "adgenerationBidAdapter": 1052,
    "microadBidAdapter": 1052,
    "geoedgeRtdProvider": 1036,
    "livewrappedBidAdapter": 983,
    "impactifyBidAdapter": 970,
    "consumableBidAdapter": 937,
    "utiqIdSystem": 925,
    "yahoosspBidAdapter": 925,
    "pxyzBidAdapter": 921,
    "mgidXBidAdapter": 912,
    "copper6sspBidAdapter": 911,
    "imuIdSystem": 908,
    "logicadBidAdapter": 902,
    "ucfunnelBidAdapter": 902,
    "bidViewabilityIO": 869,
    "yieldlabBidAdapter": 864,
    "voxBidAdapter": 860,
    "limelightDigitalBidAdapter": 858,
    "adnuntiusBidAdapter": 858,
    "stroeerCoreBidAdapter": 852,
    "gamoshiBidAdapter": 848,
    "prebidJSDebugUI": 839,
    "experianRtdProvider": 836,
    "telariaBidAdapter": 831,
    "aniviewBidAdapter": 829,
    "ajaBidAdapter": 829,
    "feedadBidAdapter": 825,
    "browsiRtdProvider": 820,
    "viantOrtbBidAdapter": 812,
    "dspxBidAdapter": 808,
    "adqueryBidAdapter": 800,
    "yandexIdSystem": 796,
    "smartxBidAdapter": 794,
    "underdogmediaBidAdapter": 794,
    "deepintentBidAdapter": 788,
    "dsaControl": 788,
    "trafficgateBidAdapter": 787,
    "gmosspBidAdapter": 785,
    "orbidderBidAdapter": 785,
    "audiencerunBidAdapter": 779,
    "luceadBidAdapter": 774,
    "deepintentDpesIdSystem": 770,
    "relevantdigitalBidAdapter": 770,
    "eskimiBidAdapter": 769,
    "topLevelPaapi": 768,
    "livewrappedAnalyticsAdapter": 767,
    "multibid": 758,
    "smartyadsBidAdapter": 755,
    "verizonMediaIdSystem": 742,
    "raynRtdProvider": 735,
    "h12mediaBidAdapter": 724,
    "acuityadsBidAdapter": 711,
    "beachfrontBidAdapter": 711,
    "braveBidAdapter": 708,
    "yandexAnalyticsAdapter": 707,
    "novatiqIdSystem": 694,
    "validationFpdModule": 694,
    "anonymisedRtdProvider": 691,
    "parrableIdSystem": 689,
    "agmaAnalyticsAdapter": 688,
    "r2b2BidAdapter": 682,
    "adqueryIdSystem": 682,
    "naveggIdSystem": 682,
    "optimeraRtdProvider": 674,
    "adtelligentIdSystem": 671,
    "iqzoneBidAdapter": 670,
    "holidBidAdapter": 669,
    "smarthubBidAdapter": 665,
    "bidscubeBidAdapter": 661,
    "discoveryBidAdapter": 659,
    "utiqMtpIdSystem": 657,
    "datablocksBidAdapter": 652,
    "conceptxBidAdapter": 651,
    "dfpAdpod": 650,
    "zeotapIdPlusIdSystem": 650,
    "performaxBidAdapter": 647,
    "adrinoBidAdapter": 643,
    "51DegreesRtdProvider": 642,
    "gothamadsBidAdapter": 638,
    "lockerdomeBidAdapter": 636,
    "mobianRtdProvider": 635,
    "ceeIdSystem": 634,
    "readpeakBidAdapter": 634,
    "lockrAIMIdSystem": 633,
    "categoryTranslation": 629,
    "medianetRtdProvider": 625,
    "pubxBidAdapter": 619,
    "bidmaticBidAdapter": 617,
    "cpmstarBidAdapter": 617,
    "pixfutureBidAdapter": 617,
    "nobidAnalyticsAdapter": 616,
    "idImportLibrary": 615,
    "blastoBidAdapter": 609,
    "pangleBidAdapter": 609,
    "e_volutionBidAdapter": 609,
    "ccxBidAdapter": 607,
    "incrxBidAdapter": 606,
    "colombiaBidAdapter": 603,
    "adtrueBidAdapter": 601,
    "adoceanBidAdapter": 601,
    "carodaBidAdapter": 601,
    "adfusionBidAdapter": 599,
    "idxIdSystem": 599,
    "netIdSystem": 599,
    "jwplayerBidAdapter": 596,
    "eightPodBidAdapter": 593,
    "optableBidAdapter": 593,
    "relevatehealthBidAdapter": 593,
    "exadsBidAdapter": 593,
    "qtBidAdapter": 593,
    "playdigoBidAdapter": 593,
    "twistDigitalBidAdapter": 593,
    "driftpixelBidAdapter": 593,
    "ringieraxelspringerBidAdapter": 593,
    "beopBidAdapter": 593,
    "gravitoIdSystem": 593,
    "pubwiseBidAdapter": 593,
    "craftBidAdapter": 591,
    "dchain": 587,
    "otmBidAdapter": 587,
    "asealBidAdapter": 586,
    "relaidoBidAdapter": 586,
    "adprimeBidAdapter": 585,
    "cwireBidAdapter": 585,
    "adstirBidAdapter": 583,
    "tncIdSystem": 582,
    "weboramaRtdProvider": 578,
    "connatixBidAdapter": 576,
    "tappxBidAdapter": 576,
    "krushmediaBidAdapter": 573,
    "czechAdIdSystem": 570,
    "dsp_genieeBidAdapter": 569,
    "auctionUserDetails": 568,
    "dmdIdSystem": 563,
    "geolocationRtdProvider": 563,
    "brandmetricsRtdProvider": 558,
    "adsinteractiveBidAdapter": 556,
    "relevadRtdProvider": 555,
    "adplusBidAdapter": 551,
    "mediasquareBidAdapter": 551,
    "admediaBidAdapter": 547,
    "orakiBidAdapter": 545,
    "admixerIdSystem": 545,
    "asoBidAdapter": 543,
    "seedingAllianceBidAdapter": 542,
    "vdoaiBidAdapter": 542,
    "goldfishAdsRtdProvider": 541,
    "jixieBidAdapter": 541,
    "openwebBidAdapter": 539,
    "greenbidsRtdProvider": 538,
    "express": 537,
    "vrtcalBidAdapter": 537,
    "geoDetection": 537,
    "operaadsBidAdapter": 533,
    "intersectionRtdProvider": 532,
    "a1MediaRtdProvider": 531,
    "pianoDmpAnalyticsAdapter": 531,
    "adpartnerBidAdapter": 530,
    "lunamediahbBidAdapter": 530,
    "videobyteBidAdapter": 530,
    "byDataAnalyticsAdapter": 529,
    "bidglassBidAdapter": 528,
    "freeWheelAdserverVideo": 528,
    "growthCodeRtdProvider": 527,
    "mantisBidAdapter": 527,
    "adlooxAnalyticsAdapter": 526,
    "docereeBidAdapter": 524,
    "smartytechBidAdapter": 523,
    "jwplayerVideoProvider": 523,
    "1plusXRtdProvider": 520,
    "appierBidAdapter": 520,
    "asteriobidAnalyticsAdapter": 519,
    "neuwoRtdProvider": 518,
    "proxistoreBidAdapter": 516,
    "trionBidAdapter": 515,
    "adWMGBidAdapter": 514,
    "qwarryBidAdapter": 514,
    "adriverIdSystem": 513,
    "bliinkBidAdapter": 513,
    "bridgewellBidAdapter": 513,
    "dacIdSystem": 513,
    "adnuntiusRtdProvider": 511,
    "kinessoIdSystem": 511,
    "stvBidAdapter": 511,
    "welectBidAdapter": 511,
    "adlooxAdServerVideo": 510,
    "adlooxRtdProvider": 510,
    "akamaiDapRtdProvider": 510,
    "blueconicRtdProvider": 510,
    "cleanioRtdProvider": 510,
    "dataControllerModule": 510,
    "konduitWrapper": 510,
    "mgidRtdProvider": 510,
    "mwOpenLinkIdSystem": 510,
    "oxxionRtdProvider": 510,
    "reconciliationRtdProvider": 510,
    "tapadIdSystem": 510,
    "yieldmoSyntheticInventoryModule": 510,
    "aaxBlockmeterRtdProvider": 509,
    "arcspanRtdProvider": 509,
    "confiantRtdProvider": 509,
    "growthCodeIdSystem": 509,
    "oneKeyIdSystem": 509,
    "oneKeyRtdProvider": 509,
    "concertAnalyticsAdapter": 505,
    "goldbachBidAdapter": 505,
    "etargetBidAdapter": 504,
    "adotBidAdapter": 501,
    "qortexRtdProvider": 501,
    "greenbidsAnalyticsAdapter": 500,
    "innityBidAdapter": 500,
    "koblerBidAdapter": 500,
    "opscoBidAdapter": 500,
    "admanBidAdapter": 498,
    "distroscaleBidAdapter": 498,
    "dynamicAdBoostRtdProvider": 497,
    "lemmaDigitalBidAdapter": 497,
    "mediakeysBidAdapter": 497,
    "adxpremiumAnalyticsAdapter": 496,
    "bidwatchAnalyticsAdapter": 496,
    "vlybyBidAdapter": 496,
    "axonixBidAdapter": 495,
    "clickforceBidAdapter": 495,
    "freepassIdSystem": 494,
    "mediafilterRtdProvider": 494,
    "mygaruIdSystem": 494,
    "operaadsIdSystem": 494,
    "yieldliftBidAdapter": 494,
    "dailymotionBidAdapter": 492,
    "glomexBidAdapter": 491,
    "equativBidAdapter": 490,
    "finativeBidAdapter": 490,
    "axisBidAdapter": 489,
    "globalsunBidAdapter": 487,
    "pubwiseAnalyticsAdapter": 487,
    "widespaceBidAdapter": 487,
    "kubientBidAdapter": 486,
    "talkadsBidAdapter": 486,
    "cleanmedianetBidAdapter": 485,
    "gammaBidAdapter": 485,
    "kueezBidAdapter": 485,
    "medianetAnalyticsAdapter": 485,
    "theAdxBidAdapter": 484,
    "tpmnBidAdapter": 483,
    "cointrafficBidAdapter": 482,
    "sharethroughAnalyticsAdapter": 482,
    "targetVideoBidAdapter": 482,
    "flippBidAdapter": 480,
    "relevantAnalyticsAdapter": 480,
    "coinzillaBidAdapter": 477,
    "snigelBidAdapter": 477,
    "adriverBidAdapter": 476,
    "adkernelAdnAnalyticsAdapter": 475,
    "adspiritBidAdapter": 475,
    "getintentBidAdapter": 475,
    "publirBidAdapter": 475,
    "buzzoolaBidAdapter": 474,
    "pilotxBidAdapter": 474,
    "quantcastBidAdapter": 474,
    "truereachBidAdapter": 474,
    "viouslyBidAdapter": 474,
    "adhashBidAdapter": 473,
    "appierAnalyticsAdapter": 473,
    "bucksenseBidAdapter": 473,
    "gnetBidAdapter": 473,
    "loglyliftBidAdapter": 473,
    "mytargetBidAdapter": 473,
    "pubstackAnalyticsAdapter": 473,
    "rtbsapeBidAdapter": 473,
    "browsiBidAdapter": 472,
    "interactiveOffersBidAdapter": 472,
    "invamiaBidAdapter": 472,
    "ipromBidAdapter": 472,
    "lassoBidAdapter": 472,
    "mathildeadsBidAdapter": 472,
    "optoutBidAdapter": 472,
    "yieldoneAnalyticsAdapter": 472,
    "alkimiBidAdapter": 471,
    "biddoBidAdapter": 471,
    "engageyaBidAdapter": 471,
    "nextrollBidAdapter": 471,
    "zetaBidAdapter": 471,
    "carbonAnalyticsAdapter": 470,
    "a4gBidAdapter": 470,
    "ablidaBidAdapter": 470,
    "adWMGAnalyticsAdapter": 470,
    "addefendBidAdapter": 470,
    "adkernelAdnBidAdapter": 470,
    "adnowBidAdapter": 470,
    "adrelevantisBidAdapter": 470,
    "aduptechBidAdapter": 470,
    "advangelistsBidAdapter": 470,
    "adxcgAnalyticsAdapter": 470,
    "adxcgBidAdapter": 470,
    "afpBidAdapter": 470,
    "apstreamBidAdapter": 470,
    "astraoneBidAdapter": 470,
    "automatadBidAdapter": 470,
    "big-richmediaBidAdapter": 470,
    "boldwinBidAdapter": 470,
    "brightMountainMediaBidAdapter": 470,
    "codefuelBidAdapter": 470,
    "contentexchangeBidAdapter": 470,
    "dailyhuntBidAdapter": 470,
    "datablocksAnalyticsAdapter": 470,
    "deltaprojectsBidAdapter": 470,
    "displayioBidAdapter": 470,
    "fintezaAnalyticsAdapter": 470,
    "gjirafaBidAdapter": 470,
    "growadvertisingBidAdapter": 470,
    "hadronAnalyticsAdapter": 470,
    "hybridBidAdapter": 470,
    "integr8BidAdapter": 470,
    "invisiblyAnalyticsAdapter": 470,
    "kargoAnalyticsAdapter": 470,
    "konduitAnalyticsAdapter": 470,
    "lkqdBidAdapter": 470,
    "loganBidAdapter": 470,
    "mabidderBidAdapter": 470,
    "madvertiseBidAdapter": 470,
    "malltvAnalyticsAdapter": 470,
    "malltvBidAdapter": 470,
    "marsmediaBidAdapter": 470,
    "mediaforceBidAdapter": 470,
    "mobfoxpbBidAdapter": 470,
    "my6senseBidAdapter": 470,
    "onomagicBidAdapter": 470,
    "ooloAnalyticsAdapter": 470,
    "optimonAnalyticsAdapter": 470,
    "orbitsoftBidAdapter": 470,
    "padsquadBidAdapter": 470,
    "pstudioBidAdapter": 470,
    "pubgeniusBidAdapter": 470,
    "pubperfAnalyticsAdapter": 470,
    "pulsepointAnalyticsAdapter": 470,
    "radsBidAdapter": 470,
    "rakutenBidAdapter": 470,
    "rivrAnalyticsAdapter": 470,
    "saambaaBidAdapter": 470,
    "scaleableAnalyticsAdapter": 470,
    "slimcutBidAdapter": 470,
    "smarticoBidAdapter": 470,
    "temedyaBidAdapter": 470,
    "terceptAnalyticsAdapter": 470,
    "ucfunnelAnalyticsAdapter": 470,
    "ventesBidAdapter": 470,
    "vibrantmediaBidAdapter": 470,
    "videoreachBidAdapter": 470,
    "viewdeosDXBidAdapter": 470,
    "vuukleBidAdapter": 470,
    "winrBidAdapter": 470,
    "wipesBidAdapter": 470,
    "yuktamediaAnalyticsAdapter": 470,
    "zeta_global_sspAnalyticsAdapter": 470,
    "admaruBidAdapter": 469,
    "adtrgtmeBidAdapter": 469,
    "appushBidAdapter": 469,
    "beyondmediaBidAdapter": 469,
    "c1xBidAdapter": 469,
    "chtnwBidAdapter": 469,
    "conversantAnalyticsAdapter": 469,
    "datawrkzBidAdapter": 469,
    "dianomiBidAdapter": 469,
    "growthCodeAnalyticsAdapter": 469,
    "idxBidAdapter": 469,
    "lifestreetBidAdapter": 469,
    "mediasniperBidAdapter": 469,
    "newspassidBidAdapter": 469,
    "open8BidAdapter": 469,
    "prismaBidAdapter": 469,
    "redtramBidAdapter": 469,
    "scatteredBidAdapter": 469,
    "shinezBidAdapter": 469,
    "videonowBidAdapter": 469,
    "viqeoBidAdapter": 469,
    "xeBidAdapter": 469,
    "ad2ictionBidAdapter": 468,
    "bedigitechBidAdapter": 468,
    "ivsBidAdapter": 468,
    "visiblemeasuresBidAdapter": 468,
    "emtvBidAdapter": 466,
    "anyclipBidAdapter": 462,
    "hypelabBidAdapter": 462,
    "adbutlerBidAdapter": 461,
    "33acrossAnalyticsAdapter": 460,
    "freepassBidAdapter": 458,
    "mediaimpactBidAdapter": 458,
    "pubCircleBidAdapter": 458,
    "smartyadsAnalyticsAdapter": 457,
    "ampliffyBidAdapter": 456,
    "illuminBidAdapter": 456,
    "kimberliteBidAdapter": 456,
    "docereeAdManagerBidAdapter": 455,
    "oxxionAnalyticsAdapter": 455,
    "programmaticaBidAdapter": 455,
    "ssmasBidAdapter": 455,
    "yieldloveBidAdapter": 455,
    "a1MediaBidAdapter": 454,
    "bridBidAdapter": 454,
    "dxkultureBidAdapter": 454,
    "edge226BidAdapter": 454,
    "kiviadsBidAdapter": 454,
    "lm_kiviadsBidAdapter": 454,
    "mediabramaBidAdapter": 454,
    "precisoBidAdapter": 454,
    "relayBidAdapter": 454,
    "retailspotBidAdapter": 454,
    "shinezRtbBidAdapter": 454,
    "silverpushBidAdapter": 454,
    "AsteriobidPbmAnalyticsAdapter": 453,
    "BTBidAdapter": 453,
    "eightPodAnalyticsAdapter": 453,
    "iqxBidAdapter": 453,
    "loyalBidAdapter": 453,
    "rixengineBidAdapter": 453,
    "silvermobBidAdapter": 453,
    "stnBidAdapter": 453,
    "tagorasBidAdapter": 453,
    "zmaticooBidAdapter": 453,
    "brightcomBidAdapter": 380,
    "gameraRtdProvider": 361,
    "akceloBidAdapter": 351,
    "bidtestBidAdapter": 333,
    "emx_digitalBidAdapter": 327,
    "magniteBidAdapter": 323,
    "appnexusAnalyticsAdapter": 318,
    "fanAdapter": 313,
    "ads_interactiveBidAdapter": 299,
    "carbonRtdProvider": 294,
    "bidResponseFilter": 278,
    "brightcomSSPBidAdapter": 278,
    "bizzclickBidAdapter": 278,
    "symitriDapRtdProvider": 276,
    "relevantModule": 263,
    "synacormediaBidAdapter": 261,
    "aolBidAdapter": 258,
    "spotxBidAdapter": 254,
    "netpubBidAdapter": 254,
    "inmobiBidAdapter": 249,
    "humansecurityRtdProvider": 233,
    "digitalMatterBidAdapter": 224,
    "targetVideoAdServerVideo": 221,
    "contxtfulBidAdapter": 217,
    "permutiveIdentityManagerIdSystem": 217,
    "ssp_genieeBidAdapter": 217,
    "wurflRtdProvider": 210,
    "pubriseBidAdapter": 206,
    "adhesionRichMediaFormatAdapter": 187,
    "mediaConsortiumBidAdapter": 186,
    "kueezrtbBidAdapter": 186,
    "smootBidAdapter": 178,
    "tapnativeBidAdapter": 178,
    "medianetFAnalyticsAdapter": 176,
    "excoBidAdapter": 172,
    "nexverseBidAdapter": 171,
    "ownadxBidAdapter": 170,
    "adgridBidAdapter": 170,
    "bridgeuppBidAdapter": 170,
    "djaxBidAdapter": 170,
    "eclickadsBidAdapter": 170,
    "dexertoBidAdapter": 170,
    "rewardedInterestIdSystem": 169,
    "responsiveAdsBidAdapter": 169,
    "bidtheatreBidAdapter": 169,
    "adverxoBidAdapter": 169,
    "ehealthcaresolutionsBidAdapter": 169,
    "escalaxBidAdapter": 163,
    "brainxBidAdapter": 162,
    "rediadsBidAdapter": 162,
    "bitmediaBidAdapter": 162,
    "greenbidsBidAdapter": 162,
    "madsenseBidAdapter": 162,
    "allowSizes": 144,
    "bidsizematch": 144,
    "aditude": 144,
    "mygaruRtdProvider": 143,
    "pubCommonId": 133,
    "prebidmanagerAnalyticsAdapter": 124,
    "prebidCustom": 122,
    "genieeBidAdapter": 115,
    "googleAnalyticsAdapter": 111,
    "xandrBidAdapter": 111,
    "alloxBidAdapter": 94,
    "advRedAnalyticsAdapter": 91,
    "acuityAdsBidAdapter": 85,
    "utiqSystem": 82,
    "adomikAnalyticsAdapter": 78,
    "botDetectionAndBlock": 72,
    "yollaVideoProvider": 66,
    "digitalmatterAnalyticsAdapter": 61,
    "mockBidAdapter": 57,
    "cpmstarCustomBidAdapter": 57,
    "viewabilityScoreGeneration": 51,
    "cpexAnalyticsAdapter": 47,
    "ozoneAnalyticsAdapter": 47,
    "hiveBidAdapter": 47,
    "hiveRtdProvider": 47,
    "britepoolIdSystem": 40,
    "anymindAnalyticsAdapter": 39,
    "fluctAnalyticsAdapter": 37,
    "fluctD2cIdSystem": 37,
    "inskinBidAdapter": 35,
    "awesomeAdsBidAdapter": 34,
    "cmv2AnalyticsAdapter": 32,
    "adplayerproVideoProvider": 30,
    "symitriAnalyticsAdapter": 30,
    "triplelift_nativeBidAdapter": 30,
    "manateeboostBidAdapter": 29,
    "haloIdSystem": 28,
    "seznamBidAdapter": 28,
    "adGridAnalyticsAdapter": 28,
    "idWardRtdProvider": 28,
    "sliderMediaType": 22,
    "minutemediaplusBidAdapter": 21,
    "pubmaticAutoRefresh": 20,
    "sortableBidAdapter": 19,
    "bluebillywigBidAdapter": 19,
    "rubiconAnalyticsAdapter": 19,
    "sovrnAnalyticsAdapter": 19,
    "cminternalBidAdapter": 18,
    "adbookpspBidAdapter": 17,
    "ebdrBidAdapter": 17,
    "eplanningAnalyticsAdapter": 17,
    "iqmBidAdapter": 17,
    "marsmediaAnalyticsAdapter": 17,
    "sigmoidAnalyticsAdapter": 17,
    "sonobiAnalyticsAdapter": 17,
    "staqAnalyticsAdapter": 17,
    "viewability": 17,
    "condorxBidAdapter": 17,
    "glimpseBidAdapter": 16,
    "inmarBidAdapter": 16,
    "liveyieldAnalyticsAdapter": 16,
    "mass": 16,
    "openxAnalyticsAdapter": 16,
    "rasBidAdapter": 16,
    "realvuAnalyticsAdapter": 16,
    "trustpidSystem": 16,
    "publirAnalyticsAdapter": 15,
    "captifyRtdProvider": 15,
    "openxOrtbBidAdapter": 15,
    "zeusPrimeRtdProvider": 15,
    "yaleoBidAdapter": 15,
    "kulturemediaBidAdapter": 14,
    "tealBidAdapter": 13,
    "underdogmediaAnalyticsAdapter": 13,
    "digidayAnalyticsAdapter": 12,
    "districtmDMXBidAdapter": 11,
    "blueBidAdapter": 11,
    "liveIntentRtdProvider": 11,
    "nodalsAiRtdProvider": 11,
    "stickyRichMediaFormatAdapter": 11,
    "oneVideoBidAdapter": 10,
    "bmsBidAdapter": 9,
    "adServer": 9,
    "admixerAnalyticsAdapter": 9,
    "lane4BidAdapter": 9,
    "michaoBidAdapter": 9,
    "mobkoiBidAdapter": 9,
    "mobkoiIdSystem": 9,
    "r2b2AnalyticsAdapter": 9,
    "pbrtbBidAdapter": 8,
    "adServerAdmixer": 8,
    "semantiqRtdProvider": 8,
    "ppi": 8,
    "adValidationWrapper": 7,
    "adnuntiusAnalyticsAdapter": 7,
    "mobkoiAnalyticsAdapter": 7,
    "overtoneRtdProvider": 7,
    "vlybyAnalyticsAdapter": 7,
    "premiumadsAnalyticsAdapter": 5,
    "premiumadsBidAdapter": 5,
    "flocIdSystem": 5,
    "pubmaticIdSystem": 5,
    "shortcutBidAdapter": 5,
    "previousAuctionInfo": 4,
    "admaruBidAdapter_asterio": 4,
    "gridNMBidAdapter": 4,
    "alfasenseBidAdapter": 3,
    "pubCommonIdSystem": 3,
    "mc_hook": 3,
    "adipoloBidAdapter": 3,
    "browsiAnalyticsAdapter": 3,
    "dochaseBidAdapter": 3,
    "mediaeyesBidAdapter": 3,
    "openPairIdSystem": 3,
    "optableRtdProvider": 3,
    "pubmaticRtdProvider": 3,
    "robustaBidAdapter": 3,
    "stackadaptBidAdapter": 3,
    "uniquestAnalyticsAdapter": 3,
    "uniquestBidAdapter": 3,
    "vistarsBidAdapter": 3,
    "peelRichMediaFormatAdapter": 3,
    "engagefrontBidAdapter": 3,
    "adfBidAdapter_1269": 2,
    "adfBidAdapter_1270": 2,
    "adfBidAdapter_1271": 2,
    "adfBidAdapter_1272": 2,
    "adfBidAdapter_1273": 2,
    "adfBidAdapter_637": 2,
    "adfBidAdapter_638": 2,
    "adfBidAdapter_639": 2,
    "adfBidAdapter_640": 2,
    "adfBidAdapter_670": 2,
    "adfBidAdapter_760": 2,
    "adfBidAdapter_761": 2,
    "appnexusBidAdapter_671": 2,
    "appnexusBidAdapter_672": 2,
    "appnexusBidAdapter_673": 2,
    "appnexusBidAdapter_674": 2,
    "appnexusBidAdapter_675": 2,
    "appnexusBidAdapter_786": 2,
    "appnexusBidAdapter_787": 2,
    "appnexusBidAdapter_788": 2,
    "appnexusBidAdapter_789": 2,
    "rubiconBidAdapter_686": 2,
    "rubiconBidAdapter_687": 2,
    "rubiconBidAdapter_688": 2,
    "rubiconBidAdapter_689": 2,
    "rubiconBidAdapter_690": 2,
    "sovrnBidAdapter_676": 2,
    "sovrnBidAdapter_677": 2,
    "sovrnBidAdapter_678": 2,
    "sovrnBidAdapter_679": 2,
    "sovrnBidAdapter_680": 2,
    "visxBidAdapter_1427": 2,
    "visxBidAdapter_1428": 2,
    "visxBidAdapter_1429": 2,
    "visxBidAdapter_1430": 2,
    "visxBidAdapter_1431": 2,
    "visxBidAdapter_1450": 2,
    "visxBidAdapter_1451": 2,
    "rtbhouseAnalyticsAdapter": 2,
    "v$prebid.modulesList$": 2,
    "customNativeLogic": 2,
    "undradsAnalyticsAdapter": 2,
    "clutch": 2,
    "adServerDFP": 2,
    "MMBidAdapter": 2,
    "afyAnalyticsAdapter": 2,
    "trustxBidAdapter": 2,
    "userIdTargeting": 2,
    "guAnalyticsAdapter": 2,
    "interstitialRichMediaFormatAdapter": 2,
    "excoPlayerBidAdapter": 2,
    "engageFrontAdapter": 2,
    "adcolonyBidAdapter": 1,
    "hjAnalyticsAdapter": 1,
    "adfBidAdapter_144": 1,
    "adfBidAdapter_146": 1,
    "adfBidAdapter_152": 1,
    "adfBidAdapter_1523": 1,
    "adfBidAdapter_1524": 1,
    "adfBidAdapter_1525": 1,
    "adfBidAdapter_1526": 1,
    "adfBidAdapter_215": 1,
    "adfBidAdapter_297": 1,
    "adfBidAdapter_298": 1,
    "adfBidAdapter_304": 1,
    "adfBidAdapter_305": 1,
    "adtelligentBidAdapter_341": 1,
    "adtelligentBidAdapter_342": 1,
    "adtelligentBidAdapter_344": 1,
    "adtelligentBidAdapter_345": 1,
    "appnexusBidAdapter_1002": 1,
    "appnexusBidAdapter_1003": 1,
    "appnexusBidAdapter_1004": 1,
    "appnexusBidAdapter_1005": 1,
    "rubiconBidAdapter_1114": 1,
    "rubiconBidAdapter_1115": 1,
    "rubiconBidAdapter_1116": 1,
    "rubiconBidAdapter_1117": 1,
    "visxBidAdapter_1584": 1,
    "visxBidAdapter_1585": 1,
    "visxBidAdapter_1586": 1,
    "visxBidAdapter_1587": 1,
    "adfBidAdapter_1827": 1,
    "adfBidAdapter_1829": 1,
    "adfBidAdapter_1832": 1,
    "adfBidAdapter_1834": 1,
    "adfBidAdapter_1952": 1,
    "adfBidAdapter_1953": 1,
    "adfBidAdapter_1954": 1,
    "visxBidAdapter_1828": 1,
    "visxBidAdapter_1830": 1,
    "visxBidAdapter_1833": 1,
    "visxBidAdapter_1835": 1,
    "akamaiDAPIdSystem": 1,
    "haloRtdProvider": 1,
    "nextrollIdSystem": 1,
    "sortableAnalyticsAdapter": 1,
    "adfBidAdapter_1204": 1,
    "adfBidAdapter_1211": 1,
    "adfBidAdapter_1218": 1,
    "adfBidAdapter_1225": 1,
    "adfBidAdapter_1232": 1,
    "adfBidAdapter_1239": 1,
    "adfBidAdapter_1246": 1,
    "adfBidAdapter_1722": 1,
    "adfBidAdapter_1723": 1,
    "adfBidAdapter_1724": 1,
    "adfBidAdapter_1725": 1,
    "adfBidAdapter_1726": 1,
    "adfBidAdapter_524": 1,
    "adfBidAdapter_582": 1,
    "adfBidAdapter_583": 1,
    "adfBidAdapter_584": 1,
    "adfBidAdapter_596": 1,
    "adfBidAdapter_597": 1,
    "adfBidAdapter_598": 1,
    "adfBidAdapter_840": 1,
    "adfBidAdapter_841": 1,
    "adfBidAdapter_842": 1,
    "visxBidAdapter_1601": 1,
    "visxBidAdapter_1602": 1,
    "visxBidAdapter_1603": 1,
    "visxBidAdapter_1604": 1,
    "visxBidAdapter_1605": 1,
    "ezBidAdapter": 1,
    "adfBidAdapter_1745": 1,
    "adfBidAdapter_1746": 1,
    "adfBidAdapter_1747": 1,
    "adfBidAdapter_540": 1,
    "adfBidAdapter_541": 1,
    "adfBidAdapter_542": 1,
    "appnexusBidAdapter_924": 1,
    "appnexusBidAdapter_925": 1,
    "appnexusBidAdapter_926": 1,
    "rubiconBidAdapter_1124": 1,
    "rubiconBidAdapter_1125": 1,
    "rubiconBidAdapter_1126": 1,
    "sovrnBidAdapter_863": 1,
    "sovrnBidAdapter_865": 1,
    "sovrnBidAdapter_867": 1,
    "visxBidAdapter_1966": 1,
    "visxBidAdapter_1967": 1,
    "cpexIdSystem": 1,
    "adformBidAdapter": 1,
    "adsquirrelRtdProvider": 1,
    "amznBidAdapter": 1,
    "ocmPbaAdapter": 1,
    "excoPublisherDemand": 1,
    "pubMaticIdSystem": 1,
    "spoternAnalyticsAdapter": 1,
    "testBannerBidAdapter": 1,
    "testVideoBidAdapter": 1,
    "underdogmediaBidAdapter-custom": 1,
    "autoRefresh": 1,
    "rubiconBrowserBidAdapter": 1,
    "valuadBidAdapter": 1
  }
}