[
  {
    "libraries": [
      "googletag"
    ],
    "identitySolutions": [],
    "cdpPlatforms": [
      "Segment"
    ],
    "cmpInfo": {
      "ccpaApplies": true,
      "uspString": "1YN-"
    },
    "unknownAdTech": [],
    "date": "2025-07-12",
    "prebidInstances": [],
    "url": "https://washingtontechnology.com"
  },
  {
    "libraries": [
      "apstag",
      "googletag",
      "ats"
    ],
    "identitySolutions": [],
    "cdpPlatforms": [],
    "cmpInfo": {
      "ccpaApplies": true,
      "uspString": "1YNY"
    },
    "unknownAdTech": [],
    "date": "2025-07-12",
    "prebidInstances": [
      {
        "globalVarName": "pbjs",
        "version": "v9.37.0",
        "modules": [
          "allowActivities",
          "appnexusBidAdapter",
          "connectIdSystem",
          "consentManagementUsp",
          "criteoBidAdapter",
          "criteoIdSystem",
          "dfpAdServerVideo",
          "genericAnalyticsAdapter",
          "gptPreAuction",
          "gridBidAdapter",
          "gumgumBidAdapter",
          "id5IdSystem",
          "identityLinkIdSystem",
          "pairIdSystem",
          "ixBidAdapter",
          "kargoBidAdapter",
          "merkleIdSystem",
          "nativoBidAdapter",
          "openxBidAdapter",
          "ozoneBidAdapter",
          "prebidServerBidAdapter",
          "priceFloors",
          "pubmaticBidAdapter",
          "rtbhouseBidAdapter",
          "rtdModule",
          "rubiconBidAdapter",
          "schain",
          "sharedIdSystem",
          "sharethroughBidAdapter",
          "stackadaptBidAdapter",
          "sizeMapping",
          "teadsBidAdapter",
          "tripleliftBidAdapter",
          "ttdBidAdapter",
          "undertoneBidAdapter",
          "unifiedIdSystem",
          "uid2IdSystem_shared",
          "uid2IdSystem",
          "unrulyBidAdapter",
          "userId",
          "yahooAdsBidAdapter",
          "fabrickIdSystem",
          "ftrackIdSystem",
          "33acrossIdSystem",
          "33acrossBidAdapter",
          "paapi",
          "paapiForGpt",
          "liveIntentIdSystem",
          "lotamePanoramaIdSystem",
          "lmpIdSystem",
          "linkedInAdsIdSystem",
          "currency"
        ]
      }
    ],
    "toolMetadata": {
      "prebidInitStates": {
        "pbjs": "complete"
      }
    },
    "url": "https://alphahistory.com"
  },
  {
    "libraries": [
      "googletag"
    ],
    "identitySolutions": [],
    "cdpPlatforms": [],
    "cmpInfo": {},
    "unknownAdTech": [],
    "date": "2025-07-12",
    "prebidInstances": [],
    "url": "https://pinkradio.com"
  },
  {
    "libraries": [
      "googletag"
    ],
    "identitySolutions": [],
    "cdpPlatforms": [],
    "cmpInfo": {},
    "unknownAdTech": [],
    "date": "2025-07-12",
    "prebidInstances": [],
    "url": "https://contadormx.com"
  },
  {
    "libraries": [
      "googletag"
    ],
    "identitySolutions": [],
    "cdpPlatforms": [],
    "cmpInfo": {
      "tcfVersion": "1.x"
    },
    "unknownAdTech": [],
    "date": "2025-07-12",
    "prebidInstances": [],
    "url": "https://embarrados.com"
  },
  {
    "libraries": [
      "googletag"
    ],
    "identitySolutions": [],
    "cdpPlatforms": [],
    "cmpInfo": {},
    "unknownAdTech": [],
    "date": "2025-07-12",
    "prebidInstances": [],
    "url": "https://axiang.cc"
  },
  {
    "libraries": [
      "googletag",
      "Criteo"
    ],
    "identitySolutions": [],
    "cdpPlatforms": [
      "Adobe"
    ],
    "cmpInfo": {
      "name": "TrustArc"
    },
    "unknownAdTech": [],
    "date": "2025-07-12",
    "prebidInstances": [],
    "url": "https://staffingindustry.com"
  },
  {
    "libraries": [
      "googletag"
    ],
    "identitySolutions": [],
    "cdpPlatforms": [
      "Tealium"
    ],
    "cmpInfo": {},
    "unknownAdTech": [],
    "date": "2025-07-12",
    "prebidInstances": [],
    "url": "https://teampages.com"
  },
  {
    "libraries": [
      "googletag"
    ],
    "identitySolutions": [],
    "cdpPlatforms": [],
    "cmpInfo": {},
    "unknownAdTech": [],
    "date": "2025-07-12",
    "prebidInstances": [],
    "url": "https://theathleticbuild.com"
  },
  {
    "libraries": [
      "apstag",
      "googletag",
      "Criteo"
    ],
    "identitySolutions": [
      "UID2.0"
    ],
    "cdpPlatforms": [],
    "cmpInfo": {
      "tcfVersion": "1.x"
    },
    "unknownAdTech": [],
    "date": "2025-07-12",
    "prebidInstances": [
      {
        "globalVarName": "pbjs",
        "version": "v9.33.0",
        "modules": [
          "consentManagementTcf",
          "consentManagementUsp",
          "consentManagementGpp",
          "ixBidAdapter",
          "rubiconBidAdapter",
          "tripleliftBidAdapter",
          "schain",
          "topicsFpdModule",
          "rtdModule",
          "contxtfulRtdProvider",
          "userId",
          "identityLinkIdSystem",
          "unifiedIdSystem",
          "sharedIdSystem",
          "criteoIdSystem",
          "33acrossIdSystem",
          "pairIdSystem",
          "pubProvidedIdSystem",
          "fpdModule",
          "id5IdSystem"
        ]
      }
    ],
    "toolMetadata": {
      "prebidInitStates": {
        "pbjs": "complete"
      }
    },
    "url": "https://cheapestdestinationsblog.com"
  },
  {
    "libraries": [
      "googletag"
    ],
    "identitySolutions": [],
    "cdpPlatforms": [],
    "cmpInfo": {},
    "unknownAdTech": [],
    "date": "2025-07-12",
    "prebidInstances": [],
    "url": "https://keralabiznews.com"
  },
  {
    "libraries": [
      "googletag"
    ],
    "identitySolutions": [],
    "cdpPlatforms": [],
    "cmpInfo": {},
    "unknownAdTech": [],
    "date": "2025-07-12",
    "prebidInstances": [],
    "url": "https://99colors.net"
  },
  {
    "libraries": [
      "googletag"
    ],
    "identitySolutions": [],
    "cdpPlatforms": [],
    "cmpInfo": {
      "tcfVersion": "2.x",
      "gdprApplies": true,
      "consentString": "CQUZpPAQUZpPAAfRtBDEBzFgAAAAAAAAAAigJOwBADOAIbAhmBJ0EnYAwAOADOAGfAdsBDMCToBQSACA8cKABAQ2OgAgPHHgAQENkIAIDxyIAEAzhMACAZwpABAeOWgAgPHLgAQDOA",
      "cmpId": 31,
      "version": "1133",
      "ccpaApplies": true,
      "uspString": ""
    },
    "unknownAdTech": [],
    "date": "2025-07-12",
    "prebidInstances": [],
    "url": "https://wormser-zeitung.de"
  },
  {
    "libraries": [],
    "identitySolutions": [],
    "cdpPlatforms": [],
    "cmpInfo": {},
    "unknownAdTech": [],
    "date": "2025-07-12",
    "prebidInstances": [
      {
        "globalVarName": "pbjs",
        "version": "v9.20.0",
        "modules": [
          "adriverBidAdapter",
          "adriverIdSystem",
          "alfasenseBidAdapter",
          "allowActivities",
          "betweenBidAdapter",
          "buzzoolaBidAdapter",
          "currency",
          "intersectionRtdProvider",
          "kimberliteBidAdapter",
          "mytargetBidAdapter",
          "otmBidAdapter",
          "pairIdSystem",
          "priceFloors",
          "rtbsapeBidAdapter",
          "rtdModule",
          "sharedIdSystem",
          "userId",
          "voxBidAdapter"
        ]
      }
    ],
    "toolMetadata": {
      "prebidInitStates": {
        "pbjs": "complete"
      }
    },
    "url": "https://tvkinoradio.ru"
  },
  {
    "libraries": [
      "apstag",
      "googletag",
      "Criteo"
    ],
    "identitySolutions": [
      "UID2.0"
    ],
    "cdpPlatforms": [],
    "cmpInfo": {
      "tcfVersion": "1.x"
    },
    "unknownAdTech": [],
    "date": "2025-07-12",
    "prebidInstances": [
      {
        "globalVarName": "pbjs",
        "version": "v9.33.0",
        "modules": [
          "consentManagementTcf",
          "consentManagementUsp",
          "consentManagementGpp",
          "ixBidAdapter",
          "pubmaticBidAdapter",
          "rubiconBidAdapter",
          "tripleliftBidAdapter",
          "schain",
          "topicsFpdModule",
          "rtdModule",
          "contxtfulRtdProvider",
          "userId",
          "identityLinkIdSystem",
          "unifiedIdSystem",
          "sharedIdSystem",
          "criteoIdSystem",
          "33acrossIdSystem",
          "pairIdSystem",
          "pubProvidedIdSystem",
          "fpdModule",
          "id5IdSystem"
        ]
      }
    ],
    "toolMetadata": {
      "prebidInitStates": {
        "pbjs": "complete"
      }
    },
    "url": "https://thetravelmagazine.net"
  },
  {
    "libraries": [
      "apstag",
      "googletag",
      "Criteo"
    ],
    "identitySolutions": [
      "UID2.0"
    ],
    "cdpPlatforms": [],
    "cmpInfo": {
      "tcfVersion": "1.x"
    },
    "unknownAdTech": [],
    "date": "2025-07-12",
    "prebidInstances": [
      {
        "globalVarName": "pbjs",
        "version": "v9.33.0",
        "modules": [
          "consentManagementTcf",
          "consentManagementUsp",
          "consentManagementGpp",
          "ixBidAdapter",
          "pubmaticBidAdapter",
          "rubiconBidAdapter",
          "tripleliftBidAdapter",
          "schain",
          "topicsFpdModule",
          "rtdModule",
          "contxtfulRtdProvider",
          "userId",
          "identityLinkIdSystem",
          "unifiedIdSystem",
          "sharedIdSystem",
          "criteoIdSystem",
          "33acrossIdSystem",
          "pairIdSystem",
          "pubProvidedIdSystem",
          "fpdModule",
          "id5IdSystem"
        ]
      }
    ],
    "toolMetadata": {
      "prebidInitStates": {
        "pbjs": "complete"
      }
    },
    "url": "https://home-ec101.com"
  },
  {
    "libraries": [
      "googletag"
    ],
    "identitySolutions": [],
    "cdpPlatforms": [],
    "cmpInfo": {},
    "unknownAdTech": [],
    "date": "2025-07-12",
    "prebidInstances": [],
    "url": "https://historicodigital.com"
  },
  {
    "libraries": [
      "googletag"
    ],
    "identitySolutions": [],
    "cdpPlatforms": [],
    "cmpInfo": {
      "tcfVersion": "2.x",
      "gdprApplies": true,
      "consentString": "CQUcHcAQUcHcAAHABBENBrFgAAAAAEPgAAqIAAAWZABMNCogjLAgBCJQMIIEACgrCAigQBAAAkDBAQAmDApyBgAusJEAIAUAAwQAgABBgACAAACABCIAKACgQAAQCBQABgAQDAQAEDAACACwEAgABAdAxTAggECwASMyKDTAlAASCAlsqEEgCBBXCEIs8AggREwUAAAAABQAAIDwWAxJICVCQQBcQTQAAEAAAUQIECCTkwABQGbLUHgyfRlaYBg-YJEFMAyAIgjISDQhN60g8UhRAAAA.YAAACHwAAAAA",
      "cmpId": 7,
      "version": "1",
      "name": "Didomi"
    },
    "unknownAdTech": [],
    "date": "2025-07-12",
    "prebidInstances": [],
    "url": "https://itespresso.es"
  },
  {
    "libraries": [
      "apstag",
      "googletag",
      "ats"
    ],
    "identitySolutions": [],
    "cdpPlatforms": [],
    "cmpInfo": {
      "ccpaApplies": true,
      "uspString": "1YNY"
    },
    "unknownAdTech": [],
    "date": "2025-07-12",
    "prebidInstances": [
      {
        "globalVarName": "pbjs",
        "version": "v9.38.0",
        "modules": [
          "allowActivities",
          "appnexusBidAdapter",
          "connectIdSystem",
          "consentManagementUsp",
          "criteoBidAdapter",
          "criteoIdSystem",
          "dfpAdServerVideo",
          "genericAnalyticsAdapter",
          "gptPreAuction",
          "gridBidAdapter",
          "gumgumBidAdapter",
          "id5IdSystem",
          "identityLinkIdSystem",
          "pairIdSystem",
          "ixBidAdapter",
          "kargoBidAdapter",
          "merkleIdSystem",
          "nativoBidAdapter",
          "openxBidAdapter",
          "ozoneBidAdapter",
          "prebidServerBidAdapter",
          "priceFloors",
          "pubmaticBidAdapter",
          "rtbhouseBidAdapter",
          "rtdModule",
          "rubiconBidAdapter",
          "schain",
          "sharedIdSystem",
          "sharethroughBidAdapter",
          "stackadaptBidAdapter",
          "sizeMapping",
          "teadsBidAdapter",
          "tripleliftBidAdapter",
          "ttdBidAdapter",
          "undertoneBidAdapter",
          "unifiedIdSystem",
          "uid2IdSystem_shared",
          "uid2IdSystem",
          "unrulyBidAdapter",
          "userId",
          "yahooAdsBidAdapter",
          "fabrickIdSystem",
          "ftrackIdSystem",
          "33acrossIdSystem",
          "33acrossBidAdapter",
          "paapi",
          "paapiForGpt",
          "liveIntentIdSystem",
          "lotamePanoramaIdSystem",
          "lmpIdSystem",
          "linkedInAdsIdSystem",
          "currency"
        ]
      }
    ],
    "toolMetadata": {
      "prebidInitStates": {
        "pbjs": "complete"
      }
    },
    "url": "https://allhomerobotics.com"
  },
  {
    "libraries": [
      "googletag"
    ],
    "identitySolutions": [],
    "cdpPlatforms": [],
    "cmpInfo": {},
    "unknownAdTech": [],
    "date": "2025-07-12",
    "prebidInstances": [],
    "url": "https://earthlingorgeous.com"
  },
  {
    "libraries": [
      "googletag"
    ],
    "identitySolutions": [],
    "cdpPlatforms": [],
    "cmpInfo": {},
    "unknownAdTech": [],
    "date": "2025-07-12",
    "prebidInstances": [],
    "url": "https://handelsregister-online.net"
  },
  {
    "libraries": [
      "googletag"
    ],
    "identitySolutions": [],
    "cdpPlatforms": [],
    "cmpInfo": {},
    "unknownAdTech": [],
    "date": "2025-07-12",
    "prebidInstances": [],
    "url": "https://loehmanns.com"
  },
  {
    "libraries": [
      "apstag",
      "googletag"
    ],
    "identitySolutions": [],
    "cdpPlatforms": [],
    "cmpInfo": {
      "ccpaApplies": true,
      "uspString": "1YNY"
    },
    "unknownAdTech": [],
    "date": "2025-07-12",
    "prebidInstances": [
      {
        "globalVarName": "pbjs",
        "version": "v9.37.0",
        "modules": [
          "allowActivities",
          "appnexusBidAdapter",
          "connectIdSystem",
          "consentManagementUsp",
          "criteoBidAdapter",
          "criteoIdSystem",
          "dfpAdServerVideo",
          "genericAnalyticsAdapter",
          "gptPreAuction",
          "gridBidAdapter",
          "gumgumBidAdapter",
          "id5IdSystem",
          "identityLinkIdSystem",
          "pairIdSystem",
          "ixBidAdapter",
          "kargoBidAdapter",
          "merkleIdSystem",
          "nativoBidAdapter",
          "openxBidAdapter",
          "ozoneBidAdapter",
          "prebidServerBidAdapter",
          "priceFloors",
          "pubmaticBidAdapter",
          "rtbhouseBidAdapter",
          "rtdModule",
          "rubiconBidAdapter",
          "schain",
          "sharedIdSystem",
          "sharethroughBidAdapter",
          "stackadaptBidAdapter",
          "sizeMapping",
          "teadsBidAdapter",
          "tripleliftBidAdapter",
          "ttdBidAdapter",
          "undertoneBidAdapter",
          "unifiedIdSystem",
          "uid2IdSystem_shared",
          "uid2IdSystem",
          "unrulyBidAdapter",
          "userId",
          "yahooAdsBidAdapter",
          "fabrickIdSystem",
          "ftrackIdSystem",
          "33acrossIdSystem",
          "33acrossBidAdapter",
          "paapi",
          "paapiForGpt",
          "liveIntentIdSystem",
          "lotamePanoramaIdSystem",
          "lmpIdSystem",
          "linkedInAdsIdSystem",
          "currency"
        ]
      }
    ],
    "toolMetadata": {
      "prebidInitStates": {
        "pbjs": "complete"
      }
    },
    "url": "https://homebuiltairplanes.com"
  },
  {
    "libraries": [
      "googletag"
    ],
    "identitySolutions": [],
    "cdpPlatforms": [],
    "cmpInfo": {},
    "unknownAdTech": [],
    "date": "2025-07-12",
    "prebidInstances": [],
    "url": "https://busyboo.com"
  },
  {
    "libraries": [
      "googletag"
    ],
    "identitySolutions": [],
    "cdpPlatforms": [],
    "cmpInfo": {
      "tcfVersion": "2.x",
      "gdprApplies": false,
      "cmpId": 10,
      "version": "56",
      "ccpaApplies": true,
      "uspString": "1---"
    },
    "unknownAdTech": [],
    "date": "2025-07-12",
    "prebidInstances": [
      {
        "globalVarName": "tmzr",
        "version": "v9.39.0",
        "modules": [
          "33acrossIdSystem",
          "adagioAnalyticsAdapter",
          "adagioBidAdapter",
          "adagioRtdProvider",
          "adfBidAdapter",
          "adyoulikeBidAdapter",
          "amxBidAdapter",
          "amxIdSystem",
          "appnexusBidAdapter",
          "azerionedgeRtdProvider",
          "consentManagementTcf",
          "criteoBidAdapter",
          "criteoIdSystem",
          "currency",
          "eplanningBidAdapter",
          "fpdModule",
          "id5IdSystem",
          "improvedigitalBidAdapter",
          "justpremiumBidAdapter",
          "kueezRtbBidAdapter",
          "lotamePanoramaIdSystem",
          "missenaBidAdapter",
          "moneytizerBidAdapter",
          "nativeRendering",
          "openxBidAdapter",
          "outbrainBidAdapter",
          "prebidServerBidAdapter",
          "priceFloors",
          "pubProvidedIdSystem",
          "pubxaiAnalyticsAdapter",
          "quantcastIdSystem",
          "richaudienceBidAdapter",
          "rtbhouseBidAdapter",
          "rtdModule",
          "rubiconBidAdapter",
          "schain",
          "sharedIdSystem",
          "sharethroughBidAdapter",
          "smilewantedBidAdapter",
          "themoneytizerBidAdapter",
          "topicsFpdModule",
          "userId"
        ]
      }
    ],
    "toolMetadata": {
      "prebidInitStates": {
        "tmzr": "complete"
      }
    },
    "url": "https://tamurt.info"
  },
  {
    "libraries": [
      "googletag"
    ],
    "identitySolutions": [],
    "cdpPlatforms": [],
    "cmpInfo": {},
    "unknownAdTech": [],
    "date": "2025-07-12",
    "prebidInstances": [],
    "url": "https://taiwandaily.net"
  },
  {
    "libraries": [
      "googletag"
    ],
    "identitySolutions": [],
    "cdpPlatforms": [],
    "cmpInfo": {},
    "unknownAdTech": [],
    "date": "2025-07-12",
    "prebidInstances": [
      {
        "globalVarName": "ihowpbjs",
        "version": "v9.27.0",
        "modules": [
          "criteoIdSystem",
          "id5IdSystem",
          "lotamePanoramaIdSystem",
          "pubmaticIHAnalyticsAdapter",
          "sharedIdSystem",
          "unifiedIdSystem",
          "userId"
        ]
      },
      {
        "globalVarName": "owpbjs",
        "version": "v6.18.0",
        "modules": [
          "33acrossIdSystem",
          "consentManagement",
          "consentManagementUsp",
          "criteoIdSystem",
          "id5IdSystem",
          "identityLinkIdSystem",
          "lotamePanoramaIdSystem",
          "parrableIdSystem",
          "unifiedIdSystem",
          "userId"
        ]
      }
    ],
    "toolMetadata": {
      "prebidInitStates": {
        "ihowpbjs": "complete",
        "owpbjs": "complete"
      }
    },
    "url": "https://daily-times.com"
  },
  {
    "libraries": [
      "googletag"
    ],
    "identitySolutions": [],
    "cdpPlatforms": [],
    "cmpInfo": {},
    "unknownAdTech": [],
    "date": "2025-07-12",
    "prebidInstances": [],
    "url": "https://infospyware.com"
  },
  {
    "libraries": [
      "googletag"
    ],
    "identitySolutions": [],
    "cdpPlatforms": [],
    "cmpInfo": {
      "tcfVersion": "2.x",
      "gdprApplies": false,
      "cmpId": 63,
      "version": "5"
    },
    "unknownAdTech": [],
    "date": "2025-07-12",
    "prebidInstances": [],
    "url": "https://palico.com"
  },
  {
    "libraries": [
      "googletag"
    ],
    "identitySolutions": [],
    "cdpPlatforms": [],
    "cmpInfo": {
      "tcfVersion": "2.x",
      "gdprApplies": true,
      "consentString": "CQUcHcAQUcHcAAcABBDEBzFgAAAAAEPgAChQAAAWwABMNCogjLIgRCJQMIIEACgrCACgQBAAAkDRAQAmDApyBgAusJkAIAUAAwQAgABBgACAAASABCIAKACAQAAQCBQABgAQBAQAMDAAGACwEAgABAdAxTAggECwASMyKDTAlAASCAlsqEEgCBBXCEIs8AggREwUAAAIABQEAADwWAhJICViQQBcQTQAAEAAAUQIECKRswBBQGaLQXgyfRkaYBg-YJklMAyAIgjIyTYhN-Ew8chRCghyAAAA.YAAACHwAAAAA",
      "cmpId": 28,
      "version": "1",
      "name": "OneTrust"
    },
    "unknownAdTech": [],
    "date": "2025-07-12",
    "prebidInstances": [],
    "url": "https://spontacts.com"
  },
  {
    "libraries": [
      "googletag"
    ],
    "identitySolutions": [],
    "cdpPlatforms": [],
    "cmpInfo": {
      "name": "OneTrust",
      "gdprApplies": false
    },
    "unknownAdTech": [],
    "date": "2025-07-12",
    "prebidInstances": [],
    "url": "https://just-drinks.com"
  },
  {
    "libraries": [
      "apstag",
      "googletag",
      "ats"
    ],
    "identitySolutions": [],
    "cdpPlatforms": [],
    "cmpInfo": {
      "ccpaApplies": true,
      "uspString": "1YNY"
    },
    "unknownAdTech": [],
    "date": "2025-07-12",
    "prebidInstances": [
      {
        "globalVarName": "pbjs",
        "version": "v9.37.0",
        "modules": [
          "allowActivities",
          "appnexusBidAdapter",
          "connectIdSystem",
          "consentManagementUsp",
          "criteoBidAdapter",
          "criteoIdSystem",
          "dfpAdServerVideo",
          "genericAnalyticsAdapter",
          "gptPreAuction",
          "gridBidAdapter",
          "gumgumBidAdapter",
          "id5IdSystem",
          "identityLinkIdSystem",
          "pairIdSystem",
          "ixBidAdapter",
          "kargoBidAdapter",
          "merkleIdSystem",
          "nativoBidAdapter",
          "openxBidAdapter",
          "ozoneBidAdapter",
          "prebidServerBidAdapter",
          "priceFloors",
          "pubmaticBidAdapter",
          "rtbhouseBidAdapter",
          "rtdModule",
          "rubiconBidAdapter",
          "schain",
          "sharedIdSystem",
          "sharethroughBidAdapter",
          "stackadaptBidAdapter",
          "sizeMapping",
          "teadsBidAdapter",
          "tripleliftBidAdapter",
          "ttdBidAdapter",
          "undertoneBidAdapter",
          "unifiedIdSystem",
          "uid2IdSystem_shared",
          "uid2IdSystem",
          "unrulyBidAdapter",
          "userId",
          "yahooAdsBidAdapter",
          "fabrickIdSystem",
          "ftrackIdSystem",
          "33acrossIdSystem",
          "33acrossBidAdapter",
          "paapi",
          "paapiForGpt",
          "liveIntentIdSystem",
          "lotamePanoramaIdSystem",
          "lmpIdSystem",
          "linkedInAdsIdSystem",
          "currency"
        ]
      }
    ],
    "toolMetadata": {
      "prebidInitStates": {
        "pbjs": "complete"
      }
    },
    "url": "https://thehomeschoolmom.com"
  },
  {
    "libraries": [
      "googletag"
    ],
    "identitySolutions": [],
    "cdpPlatforms": [],
    "cmpInfo": {},
    "unknownAdTech": [],
    "date": "2025-07-12",
    "prebidInstances": [],
    "url": "https://ketawa.com"
  },
  {
    "libraries": [
      "googletag"
    ],
    "identitySolutions": [],
    "cdpPlatforms": [],
    "cmpInfo": {},
    "unknownAdTech": [],
    "date": "2025-07-12",
    "prebidInstances": [],
    "url": "https://dataunion.org"
  },
  {
    "libraries": [
      "apstag",
      "googletag",
      "Criteo"
    ],
    "identitySolutions": [
      "UID2.0"
    ],
    "cdpPlatforms": [],
    "cmpInfo": {},
    "unknownAdTech": [],
    "date": "2025-07-12",
    "prebidInstances": [
      {
        "globalVarName": "vlipb",
        "version": "v9.42.0",
        "modules": [
          "adagioBidAdapter",
          "adagioRtdProvider",
          "adtelligentBidAdapter",
          "amxBidAdapter",
          "amxIdSystem",
          "apacdexBidAdapter",
          "appnexusBidAdapter",
          "bidtestBidAdapter",
          "consentManagementTcf",
          "consentManagementUsp",
          "conversantBidAdapter",
          "criteoBidAdapter",
          "criteoIdSystem",
          "currency",
          "dfpAdServerVideo",
          "eplanningBidAdapter",
          "experianRtdProvider",
          "id5IdSystem",
          "intentIqIdSystem",
          "ixBidAdapter",
          "onetagBidAdapter",
          "openxBidAdapter",
          "paapi",
          "paapiForGpt",
          "pubProvidedIdSystem",
          "pubmaticBidAdapter",
          "richaudienceBidAdapter",
          "riseBidAdapter",
          "rtbhouseBidAdapter",
          "rtdModule",
          "schain",
          "seedtagBidAdapter",
          "sharedIdSystem",
          "sharethroughBidAdapter",
          "smaatoBidAdapter",
          "smartadserverBidAdapter",
          "smilewantedBidAdapter",
          "sonobiBidAdapter",
          "sovrnBidAdapter",
          "taboolaBidAdapter",
          "tcfControl",
          "teadsBidAdapter",
          "tripleliftBidAdapter",
          "ucfunnelBidAdapter",
          "uid2IdSystem",
          "unrulyBidAdapter",
          "userId",
          "verizonMediaIdSystem",
          "vidazooBidAdapter"
        ]
      }
    ],
    "toolMetadata": {
      "prebidInitStates": {
        "vlipb": "complete"
      }
    },
    "url": "https://examsegg.com"
  },
  {
    "libraries": [
      "googletag"
    ],
    "identitySolutions": [],
    "cdpPlatforms": [],
    "cmpInfo": {},
    "unknownAdTech": [],
    "date": "2025-07-12",
    "prebidInstances": [],
    "url": "https://freebeerandhotwings.com"
  },
  {
    "libraries": [
      "googletag"
    ],
    "identitySolutions": [],
    "cdpPlatforms": [],
    "cmpInfo": {},
    "unknownAdTech": [],
    "date": "2025-07-12",
    "prebidInstances": [],
    "url": "https://loscuentos.net"
  },
  {
    "libraries": [
      "apstag",
      "googletag",
      "ats"
    ],
    "identitySolutions": [],
    "cdpPlatforms": [],
    "cmpInfo": {
      "ccpaApplies": true,
      "uspString": "1YNY"
    },
    "unknownAdTech": [],
    "date": "2025-07-12",
    "prebidInstances": [
      {
        "globalVarName": "pbjs",
        "version": "v9.37.0",
        "modules": [
          "allowActivities",
          "appnexusBidAdapter",
          "connectIdSystem",
          "consentManagementUsp",
          "criteoBidAdapter",
          "criteoIdSystem",
          "dfpAdServerVideo",
          "genericAnalyticsAdapter",
          "gptPreAuction",
          "gridBidAdapter",
          "gumgumBidAdapter",
          "id5IdSystem",
          "identityLinkIdSystem",
          "pairIdSystem",
          "ixBidAdapter",
          "kargoBidAdapter",
          "merkleIdSystem",
          "nativoBidAdapter",
          "openxBidAdapter",
          "ozoneBidAdapter",
          "prebidServerBidAdapter",
          "priceFloors",
          "pubmaticBidAdapter",
          "rtbhouseBidAdapter",
          "rtdModule",
          "rubiconBidAdapter",
          "schain",
          "sharedIdSystem",
          "sharethroughBidAdapter",
          "stackadaptBidAdapter",
          "sizeMapping",
          "teadsBidAdapter",
          "tripleliftBidAdapter",
          "ttdBidAdapter",
          "undertoneBidAdapter",
          "unifiedIdSystem",
          "uid2IdSystem_shared",
          "uid2IdSystem",
          "unrulyBidAdapter",
          "userId",
          "yahooAdsBidAdapter",
          "fabrickIdSystem",
          "ftrackIdSystem",
          "33acrossIdSystem",
          "33acrossBidAdapter",
          "paapi",
          "paapiForGpt",
          "liveIntentIdSystem",
          "lotamePanoramaIdSystem",
          "lmpIdSystem",
          "linkedInAdsIdSystem",
          "currency"
        ]
      }
    ],
    "toolMetadata": {
      "prebidInitStates": {
        "pbjs": "complete"
      }
    },
    "url": "https://goodcarbadcar.net"
  },
  {
    "libraries": [
      "apstag",
      "googletag",
      "ats"
    ],
    "identitySolutions": [],
    "cdpPlatforms": [],
    "cmpInfo": {
      "ccpaApplies": true,
      "uspString": "1YNY"
    },
    "unknownAdTech": [],
    "date": "2025-07-12",
    "prebidInstances": [
      {
        "globalVarName": "pbjs",
        "version": "v9.37.0",
        "modules": [
          "allowActivities",
          "appnexusBidAdapter",
          "connectIdSystem",
          "consentManagementUsp",
          "criteoBidAdapter",
          "criteoIdSystem",
          "dfpAdServerVideo",
          "genericAnalyticsAdapter",
          "gptPreAuction",
          "gridBidAdapter",
          "gumgumBidAdapter",
          "id5IdSystem",
          "identityLinkIdSystem",
          "pairIdSystem",
          "ixBidAdapter",
          "kargoBidAdapter",
          "merkleIdSystem",
          "nativoBidAdapter",
          "openxBidAdapter",
          "ozoneBidAdapter",
          "prebidServerBidAdapter",
          "priceFloors",
          "pubmaticBidAdapter",
          "rtbhouseBidAdapter",
          "rtdModule",
          "rubiconBidAdapter",
          "schain",
          "sharedIdSystem",
          "sharethroughBidAdapter",
          "stackadaptBidAdapter",
          "sizeMapping",
          "teadsBidAdapter",
          "tripleliftBidAdapter",
          "ttdBidAdapter",
          "undertoneBidAdapter",
          "unifiedIdSystem",
          "uid2IdSystem_shared",
          "uid2IdSystem",
          "unrulyBidAdapter",
          "userId",
          "yahooAdsBidAdapter",
          "fabrickIdSystem",
          "ftrackIdSystem",
          "33acrossIdSystem",
          "33acrossBidAdapter",
          "paapi",
          "paapiForGpt",
          "liveIntentIdSystem",
          "lotamePanoramaIdSystem",
          "lmpIdSystem",
          "linkedInAdsIdSystem",
          "currency"
        ]
      }
    ],
    "toolMetadata": {
      "prebidInitStates": {
        "pbjs": "complete"
      }
    },
    "url": "https://toddlerapproved.com"
  },
  {
    "libraries": [
      "googletag"
    ],
    "identitySolutions": [],
    "cdpPlatforms": [
      "Segment"
    ],
    "cmpInfo": {},
    "unknownAdTech": [],
    "date": "2025-07-12",
    "prebidInstances": [],
    "url": "https://eastvalleytribune.com"
  },
  {
    "libraries": [
      "googletag",
      "Criteo"
    ],
    "identitySolutions": [],
    "cdpPlatforms": [],
    "cmpInfo": {},
    "unknownAdTech": [],
    "date": "2025-07-12",
    "prebidInstances": [
      {
        "globalVarName": "pbjs",
        "version": "v9.36.0",
        "modules": [
          "adagioAnalyticsAdapter",
          "adgenerationBidAdapter",
          "appnexusBidAdapter",
          "atsAnalyticsAdapter",
          "consentManagementTcf",
          "criteoBidAdapter",
          "criteoIdSystem",
          "currency",
          "dfpAdServerVideo",
          "dgkeywordRtdProvider",
          "fpdModule",
          "gptPreAuction",
          "gumgumBidAdapter",
          "iasRtdProvider",
          "imRtdProvider",
          "ixBidAdapter",
          "paapi",
          "paapiForGpt",
          "priceFloors",
          "pubmaticBidAdapter",
          "rtdModule",
          "rubiconBidAdapter",
          "schain",
          "tcfControl",
          "topicsFpdModule",
          "ttdBidAdapter",
          "unifiedIdSystem",
          "userId"
        ]
      }
    ],
    "toolMetadata": {
      "prebidInitStates": {
        "pbjs": "complete"
      }
    },
    "url": "https://rkk.jp"
  },
  {
    "libraries": [
      "apstag",
      "googletag",
      "Criteo"
    ],
    "identitySolutions": [
      "UID2.0",
      "ID5"
    ],
    "cdpPlatforms": [
      "Segment"
    ],
    "cmpInfo": {
      "ccpaApplies": true,
      "uspString": "1YNN"
    },
    "unknownAdTech": [],
    "date": "2025-07-12",
    "prebidInstances": [
      {
        "globalVarName": "$$PREBID_GLOBAL$$",
        "version": "v$prebid.version$",
        "modules": [
          "v$prebid.modulesList$"
        ]
      }
    ],
    "toolMetadata": {
      "prebidInitStates": {
        "$$PREBID_GLOBAL$$": "complete"
      }
    },
    "url": "https://nrtoday.com"
  },
  {
    "libraries": [
      "googletag",
      "Criteo"
    ],
    "identitySolutions": [
      "ID5"
    ],
    "cdpPlatforms": [],
    "cmpInfo": {
      "tcfVersion": "2.x",
      "gdprApplies": false,
      "consentString": "",
      "cmpId": 299,
      "version": "10"
    },
    "unknownAdTech": [],
    "date": "2025-07-12",
    "prebidInstances": [
      {
        "globalVarName": "epbjs",
        "version": "v9.43.0",
        "modules": [
          "33acrossBidAdapter",
          "33acrossIdSystem",
          "adyoulikeBidAdapter",
          "allowActivities",
          "amxBidAdapter",
          "amxIdSystem",
          "appnexusBidAdapter",
          "atsAnalyticsAdapter",
          "cadentApertureMXBidAdapter",
          "colossussspBidAdapter",
          "connectIdSystem",
          "consentManagementGpp",
          "consentManagementTcf",
          "consentManagementUsp",
          "criteoBidAdapter",
          "criteoIdSystem",
          "currency",
          "dfpAdServerVideo",
          "euidIdSystem",
          "fpdModule",
          "gptPreAuction",
          "gumgumBidAdapter",
          "hadronIdSystem",
          "id5IdSystem",
          "identityLinkIdSystem",
          "inmobiBidAdapter",
          "insticatorBidAdapter",
          "ixBidAdapter",
          "kargoBidAdapter",
          "liveIntentAnalyticsAdapter",
          "liveIntentIdSystem",
          "lotamePanoramaIdSystem",
          "medianetAnalyticsAdapter",
          "medianetBidAdapter",
          "minutemediaBidAdapter",
          "nexx360BidAdapter",
          "oguryBidAdapter",
          "onetagBidAdapter",
          "openxBidAdapter",
          "paapi",
          "paapiForGpt",
          "pairIdSystem",
          "prebidServerBidAdapter",
          "priceFloors",
          "pubProvidedIdSystem",
          "pubmaticBidAdapter",
          "quantcastIdSystem",
          "resetdigitalBidAdapter",
          "rtdModule",
          "rubiconBidAdapter",
          "schain",
          "seedtagBidAdapter",
          "sharedIdSystem",
          "sharethroughBidAdapter",
          "sizeMappingV2",
          "smartadserverBidAdapter",
          "sonobiBidAdapter",
          "sovrnBidAdapter",
          "sparteoBidAdapter",
          "tcfControl",
          "teadsBidAdapter",
          "topicsFpdModule",
          "tripleliftBidAdapter",
          "ttdBidAdapter",
          "uid2IdSystem",
          "undertoneBidAdapter",
          "unifiedIdSystem",
          "unrulyBidAdapter",
          "userId",
          "vidazooBidAdapter",
          "videoModule",
          "videojsVideoProvider",
          "yieldmoBidAdapter"
        ]
      }
    ],
    "toolMetadata": {
      "prebidInitStates": {
        "epbjs": "complete"
      }
    },
    "url": "https://suggestmemovie.com"
  },
  {
    "libraries": [
      "googletag"
    ],
    "identitySolutions": [],
    "cdpPlatforms": [],
    "cmpInfo": {},
    "unknownAdTech": [],
    "date": "2025-07-12",
    "prebidInstances": [],
    "url": "https://springtrainingonline.com"
  },
  {
    "libraries": [
      "googletag"
    ],
    "identitySolutions": [],
    "cdpPlatforms": [],
    "cmpInfo": {},
    "unknownAdTech": [],
    "date": "2025-07-12",
    "prebidInstances": [],
    "url": "https://ediva.gr"
  },
  {
    "libraries": [
      "googletag"
    ],
    "identitySolutions": [],
    "cdpPlatforms": [],
    "cmpInfo": {
      "tcfVersion": "2.x",
      "gdprApplies": false,
      "consentString": "CQUcHcAQUcHcAAcABBENBzFgAAAAAAAAACiQAAAAAAEBICoACwAKgAcABBADIANAAeABMACqAIQARAAwwB7AD9AI4AYoA4gB7QFIgKbAXmAycdAZAAWABUADgAIIAZABoADwAJgAVQBEACjAGGAMoAewA_QCLAEcAMUAcQA9oCLwFNgLzAZOAywBqo4AMAA8AC4AXQCEAHSAX0QgDgALACqARwAxQCmwGTgNVJQDgAFgAcAB4AEwAKoAiABRgEcAMUAcQBF4C8wGTgMsJAAQALlICYACwAKgAcABBADIANAAeABMACqAIgAUYAygB-gEWAI4AYoBF4CmwF5gMnKAAgALgL6A.YAAAAAAAAAAA",
      "cmpId": 28,
      "version": "1",
      "name": "OneTrust"
    },
    "unknownAdTech": [],
    "date": "2025-07-12",
    "prebidInstances": [],
    "url": "https://livenation.pl"
  },
  {
    "libraries": [
      "googletag"
    ],
    "identitySolutions": [],
    "cdpPlatforms": [],
    "cmpInfo": {},
    "unknownAdTech": [],
    "date": "2025-07-12",
    "prebidInstances": [],
    "url": "https://sawaal.com"
  },
  {
    "libraries": [
      "googletag"
    ],
    "identitySolutions": [
      "ID5"
    ],
    "cdpPlatforms": [],
    "cmpInfo": {},
    "unknownAdTech": [],
    "date": "2025-07-12",
    "prebidInstances": [
      {
        "globalVarName": "tmzr",
        "version": "v9.39.0",
        "modules": [
          "33acrossIdSystem",
          "adagioAnalyticsAdapter",
          "adagioBidAdapter",
          "adagioRtdProvider",
          "adfBidAdapter",
          "amxBidAdapter",
          "amxIdSystem",
          "appnexusBidAdapter",
          "azerionedgeRtdProvider",
          "criteoBidAdapter",
          "criteoIdSystem",
          "currency",
          "fpdModule",
          "id5IdSystem",
          "improvedigitalBidAdapter",
          "justpremiumBidAdapter",
          "kueezRtbBidAdapter",
          "lotamePanoramaIdSystem",
          "missenaBidAdapter",
          "moneytizerBidAdapter",
          "nativeRendering",
          "onetagBidAdapter",
          "openxBidAdapter",
          "outbrainBidAdapter",
          "prebidServerBidAdapter",
          "priceFloors",
          "pubProvidedIdSystem",
          "pubxaiAnalyticsAdapter",
          "quantcastIdSystem",
          "rtbhouseBidAdapter",
          "rtdModule",
          "rubiconBidAdapter",
          "schain",
          "sharedIdSystem",
          "sharethroughBidAdapter",
          "smilewantedBidAdapter",
          "themoneytizerBidAdapter",
          "topicsFpdModule",
          "userId"
        ]
      }
    ],
    "toolMetadata": {
      "prebidInitStates": {
        "tmzr": "complete"
      }
    },
    "url": "https://disneycolors.net"
  },
  {
    "libraries": [
      "googletag"
    ],
    "identitySolutions": [],
    "cdpPlatforms": [],
    "cmpInfo": {},
    "unknownAdTech": [],
    "date": "2025-07-12",
    "prebidInstances": [],
    "url": "https://blueheronhealthnews.com"
  },
  {
    "libraries": [
      "googletag"
    ],
    "identitySolutions": [],
    "cdpPlatforms": [],
    "cmpInfo": {
      "tcfVersion": "2.x",
      "gdprApplies": false,
      "cmpId": 61,
      "version": "3"
    },
    "unknownAdTech": [],
    "date": "2025-07-12",
    "prebidInstances": [],
    "url": "https://czasnawnetrze.pl"
  },
  {
    "libraries": [
      "googletag"
    ],
    "identitySolutions": [],
    "cdpPlatforms": [],
    "cmpInfo": {
      "ccpaApplies": true,
      "uspString": "1---"
    },
    "unknownAdTech": [],
    "date": "2025-07-12",
    "prebidInstances": [],
    "url": "https://robtex.org"
  },
  {
    "libraries": [
      "googletag"
    ],
    "identitySolutions": [],
    "cdpPlatforms": [],
    "cmpInfo": {},
    "unknownAdTech": [],
    "date": "2025-07-12",
    "prebidInstances": [],
    "url": "https://idsnews.com"
  },
  {
    "libraries": [
      "googletag"
    ],
    "identitySolutions": [],
    "cdpPlatforms": [],
    "cmpInfo": {},
    "unknownAdTech": [],
    "date": "2025-07-12",
    "prebidInstances": [],
    "url": "https://modsquadhockey.com"
  },
  {
    "libraries": [
      "googletag"
    ],
    "identitySolutions": [],
    "cdpPlatforms": [],
    "cmpInfo": {},
    "unknownAdTech": [],
    "date": "2025-07-12",
    "prebidInstances": [],
    "url": "https://hanmoto.com"
  },
  {
    "libraries": [
      "googletag"
    ],
    "identitySolutions": [],
    "cdpPlatforms": [],
    "cmpInfo": {},
    "unknownAdTech": [],
    "date": "2025-07-12",
    "prebidInstances": [],
    "url": "https://frmheadtotoe.com"
  },
  {
    "libraries": [
      "apstag",
      "googletag"
    ],
    "identitySolutions": [
      "UID2.0",
      "ID5"
    ],
    "cdpPlatforms": [],
    "cmpInfo": {
      "ccpaApplies": true,
      "uspString": "1---"
    },
    "unknownAdTech": [],
    "date": "2025-07-12",
    "prebidInstances": [
      {
        "globalVarName": "pbjs",
        "version": "v9.33.0",
        "modules": [
          "consentManagementTcf",
          "consentManagementUsp",
          "consentManagementGpp",
          "ixBidAdapter",
          "pubmaticBidAdapter",
          "rubiconBidAdapter",
          "tripleliftBidAdapter",
          "schain",
          "topicsFpdModule",
          "rtdModule",
          "contxtfulRtdProvider",
          "userId",
          "identityLinkIdSystem",
          "unifiedIdSystem",
          "sharedIdSystem",
          "criteoIdSystem",
          "33acrossIdSystem",
          "pairIdSystem",
          "pubProvidedIdSystem",
          "fpdModule",
          "id5IdSystem"
        ]
      }
    ],
    "toolMetadata": {
      "prebidInitStates": {
        "pbjs": "complete"
      }
    },
    "url": "https://grrrltraveler.com"
  },
  {
    "libraries": [
      "apstag",
      "googletag",
      "ats"
    ],
    "identitySolutions": [],
    "cdpPlatforms": [],
    "cmpInfo": {
      "ccpaApplies": true,
      "uspString": "1YNY"
    },
    "unknownAdTech": [],
    "date": "2025-07-12",
    "prebidInstances": [
      {
        "globalVarName": "pbjs",
        "version": "v9.37.0",
        "modules": [
          "allowActivities",
          "appnexusBidAdapter",
          "connectIdSystem",
          "consentManagementUsp",
          "criteoBidAdapter",
          "criteoIdSystem",
          "dfpAdServerVideo",
          "genericAnalyticsAdapter",
          "gptPreAuction",
          "gridBidAdapter",
          "gumgumBidAdapter",
          "id5IdSystem",
          "identityLinkIdSystem",
          "pairIdSystem",
          "ixBidAdapter",
          "kargoBidAdapter",
          "merkleIdSystem",
          "nativoBidAdapter",
          "openxBidAdapter",
          "ozoneBidAdapter",
          "prebidServerBidAdapter",
          "priceFloors",
          "pubmaticBidAdapter",
          "rtbhouseBidAdapter",
          "rtdModule",
          "rubiconBidAdapter",
          "schain",
          "sharedIdSystem",
          "sharethroughBidAdapter",
          "stackadaptBidAdapter",
          "sizeMapping",
          "teadsBidAdapter",
          "tripleliftBidAdapter",
          "ttdBidAdapter",
          "undertoneBidAdapter",
          "unifiedIdSystem",
          "uid2IdSystem_shared",
          "uid2IdSystem",
          "unrulyBidAdapter",
          "userId",
          "yahooAdsBidAdapter",
          "fabrickIdSystem",
          "ftrackIdSystem",
          "33acrossIdSystem",
          "33acrossBidAdapter",
          "paapi",
          "paapiForGpt",
          "liveIntentIdSystem",
          "lotamePanoramaIdSystem",
          "lmpIdSystem",
          "linkedInAdsIdSystem",
          "currency"
        ]
      }
    ],
    "toolMetadata": {
      "prebidInitStates": {
        "pbjs": "complete"
      }
    },
    "url": "https://smartmoneysimplelife.com"
  },
  {
    "libraries": [
      "googletag"
    ],
    "identitySolutions": [],
    "cdpPlatforms": [],
    "cmpInfo": {
      "ccpaApplies": true,
      "uspString": "1---",
      "name": "Cookiebot",
      "consentString": "-1"
    },
    "unknownAdTech": [],
    "date": "2025-07-12",
    "prebidInstances": [],
    "url": "https://brewbound.com"
  },
  {
    "libraries": [
      "googletag"
    ],
    "identitySolutions": [],
    "cdpPlatforms": [],
    "cmpInfo": {},
    "unknownAdTech": [],
    "date": "2025-07-12",
    "prebidInstances": [],
    "url": "https://unibilgi.net"
  },
  {
    "libraries": [
      "googletag"
    ],
    "identitySolutions": [],
    "cdpPlatforms": [],
    "cmpInfo": {},
    "unknownAdTech": [],
    "date": "2025-07-12",
    "prebidInstances": [],
    "url": "https://toner24.es"
  },
  {
    "libraries": [
      "googletag"
    ],
    "identitySolutions": [],
    "cdpPlatforms": [],
    "cmpInfo": {
      "tcfVersion": "2.x",
      "gdprApplies": false,
      "cmpId": 68,
      "version": "3",
      "ccpaApplies": true,
      "uspString": "1YNN"
    },
    "unknownAdTech": [],
    "date": "2025-07-12",
    "prebidInstances": [],
    "url": "https://phentermine.com"
  },
  {
    "libraries": [
      "googletag"
    ],
    "identitySolutions": [],
    "cdpPlatforms": [],
    "cmpInfo": {},
    "unknownAdTech": [],
    "date": "2025-07-12",
    "prebidInstances": [],
    "url": "https://lalineaenvivo.com"
  },
  {
    "libraries": [
      "apstag",
      "googletag",
      "ats",
      "Criteo"
    ],
    "identitySolutions": [
      "UID2.0",
      "ID5"
    ],
    "cdpPlatforms": [],
    "cmpInfo": {
      "ccpaApplies": true,
      "uspString": "1YNY",
      "name": "OneTrust",
      "gdprApplies": false
    },
    "unknownAdTech": [],
    "date": "2025-07-12",
    "prebidInstances": [
      {
        "globalVarName": "owpbjs",
        "version": "v9.27.0",
        "modules": [
          "amxBidAdapter",
          "appnexusBidAdapter",
          "auctionUserDetails",
          "consentManagementGpp",
          "consentManagementTcf",
          "consentManagementUsp",
          "dfpAdServerVideo",
          "geoDetection",
          "gppControl_usnat",
          "gppControl_usstates",
          "gptPreAuction",
          "instreamTracking",
          "ixBidAdapter",
          "medianetBidAdapter",
          "openxBidAdapter",
          "prebidJSDebugUI",
          "prebidServerBidAdapter",
          "priceFloors",
          "pubmaticAnalyticsAdapter",
          "pubmaticBidAdapter",
          "rubiconBidAdapter",
          "tcfControl",
          "undertoneBidAdapter"
        ]
      }
    ],
    "toolMetadata": {
      "prebidInitStates": {
        "owpbjs": "complete"
      }
    },
    "url": "https://volvoforums.com"
  },
  {
    "libraries": [
      "googletag"
    ],
    "identitySolutions": [],
    "cdpPlatforms": [],
    "cmpInfo": {},
    "unknownAdTech": [],
    "date": "2025-07-12",
    "prebidInstances": [],
    "url": "https://netspotapp.com"
  },
  {
    "libraries": [
      "googletag"
    ],
    "identitySolutions": [],
    "cdpPlatforms": [],
    "cmpInfo": {},
    "unknownAdTech": [],
    "date": "2025-07-12",
    "prebidInstances": [],
    "url": "https://bizarro.fm"
  },
  {
    "libraries": [
      "apstag",
      "googletag",
      "ats"
    ],
    "identitySolutions": [],
    "cdpPlatforms": [],
    "cmpInfo": {
      "ccpaApplies": true,
      "uspString": "1YNY"
    },
    "unknownAdTech": [],
    "date": "2025-07-12",
    "prebidInstances": [
      {
        "globalVarName": "pbjs",
        "version": "v9.37.0",
        "modules": [
          "allowActivities",
          "appnexusBidAdapter",
          "connectIdSystem",
          "consentManagementUsp",
          "criteoBidAdapter",
          "criteoIdSystem",
          "dfpAdServerVideo",
          "genericAnalyticsAdapter",
          "gptPreAuction",
          "gridBidAdapter",
          "gumgumBidAdapter",
          "id5IdSystem",
          "identityLinkIdSystem",
          "pairIdSystem",
          "ixBidAdapter",
          "kargoBidAdapter",
          "merkleIdSystem",
          "nativoBidAdapter",
          "openxBidAdapter",
          "ozoneBidAdapter",
          "prebidServerBidAdapter",
          "priceFloors",
          "pubmaticBidAdapter",
          "rtbhouseBidAdapter",
          "rtdModule",
          "rubiconBidAdapter",
          "schain",
          "sharedIdSystem",
          "sharethroughBidAdapter",
          "stackadaptBidAdapter",
          "sizeMapping",
          "teadsBidAdapter",
          "tripleliftBidAdapter",
          "ttdBidAdapter",
          "undertoneBidAdapter",
          "unifiedIdSystem",
          "uid2IdSystem_shared",
          "uid2IdSystem",
          "unrulyBidAdapter",
          "userId",
          "yahooAdsBidAdapter",
          "fabrickIdSystem",
          "ftrackIdSystem",
          "33acrossIdSystem",
          "33acrossBidAdapter",
          "paapi",
          "paapiForGpt",
          "liveIntentIdSystem",
          "lotamePanoramaIdSystem",
          "lmpIdSystem",
          "linkedInAdsIdSystem",
          "currency"
        ]
      }
    ],
    "toolMetadata": {
      "prebidInitStates": {
        "pbjs": "complete"
      }
    },
    "url": "https://gimmedelicious.com"
  },
  {
    "libraries": [
      "googletag"
    ],
    "identitySolutions": [],
    "cdpPlatforms": [],
    "cmpInfo": {},
    "unknownAdTech": [],
    "date": "2025-07-12",
    "prebidInstances": [],
    "url": "https://automotive-online.nl"
  },
  {
    "libraries": [
      "googletag",
      "Criteo"
    ],
    "identitySolutions": [
      "UID2.0"
    ],
    "cdpPlatforms": [],
    "cmpInfo": {
      "ccpaApplies": true,
      "uspString": "1---"
    },
    "unknownAdTech": [],
    "date": "2025-07-12",
    "prebidInstances": [],
    "url": "https://korezin.com"
  },
  {
    "libraries": [
      "googletag"
    ],
    "identitySolutions": [],
    "cdpPlatforms": [],
    "cmpInfo": {},
    "unknownAdTech": [],
    "date": "2025-07-12",
    "prebidInstances": [],
    "url": "https://yazilimmutfagi.com"
  },
  {
    "libraries": [
      "apstag",
      "googletag"
    ],
    "identitySolutions": [],
    "cdpPlatforms": [],
    "cmpInfo": {
      "ccpaApplies": true,
      "uspString": "1YNY"
    },
    "unknownAdTech": [],
    "date": "2025-07-12",
    "prebidInstances": [
      {
        "globalVarName": "pbjs",
        "version": "v9.37.0",
        "modules": [
          "allowActivities",
          "appnexusBidAdapter",
          "connectIdSystem",
          "consentManagementUsp",
          "criteoBidAdapter",
          "criteoIdSystem",
          "dfpAdServerVideo",
          "genericAnalyticsAdapter",
          "gptPreAuction",
          "gridBidAdapter",
          "gumgumBidAdapter",
          "id5IdSystem",
          "identityLinkIdSystem",
          "pairIdSystem",
          "ixBidAdapter",
          "kargoBidAdapter",
          "merkleIdSystem",
          "nativoBidAdapter",
          "openxBidAdapter",
          "ozoneBidAdapter",
          "prebidServerBidAdapter",
          "priceFloors",
          "pubmaticBidAdapter",
          "rtbhouseBidAdapter",
          "rtdModule",
          "rubiconBidAdapter",
          "schain",
          "sharedIdSystem",
          "sharethroughBidAdapter",
          "stackadaptBidAdapter",
          "sizeMapping",
          "teadsBidAdapter",
          "tripleliftBidAdapter",
          "ttdBidAdapter",
          "undertoneBidAdapter",
          "unifiedIdSystem",
          "uid2IdSystem_shared",
          "uid2IdSystem",
          "unrulyBidAdapter",
          "userId",
          "yahooAdsBidAdapter",
          "fabrickIdSystem",
          "ftrackIdSystem",
          "33acrossIdSystem",
          "33acrossBidAdapter",
          "paapi",
          "paapiForGpt",
          "liveIntentIdSystem",
          "lotamePanoramaIdSystem",
          "lmpIdSystem",
          "linkedInAdsIdSystem",
          "currency"
        ]
      }
    ],
    "toolMetadata": {
      "prebidInitStates": {
        "pbjs": "complete"
      }
    },
    "url": "https://wendaful.com"
  },
  {
    "libraries": [
      "Criteo"
    ],
    "identitySolutions": [],
    "cdpPlatforms": [],
    "cmpInfo": {},
    "unknownAdTech": [],
    "date": "2025-07-12",
    "prebidInstances": [],
    "url": "https://damasjewellery.com"
  },
  {
    "libraries": [
      "googletag"
    ],
    "identitySolutions": [],
    "cdpPlatforms": [],
    "cmpInfo": {},
    "unknownAdTech": [],
    "date": "2025-07-12",
    "prebidInstances": [],
    "url": "https://zakka.net"
  },
  {
    "libraries": [
      "Criteo"
    ],
    "identitySolutions": [],
    "cdpPlatforms": [
      "Adobe"
    ],
    "cmpInfo": {},
    "unknownAdTech": [],
    "date": "2025-07-12",
    "prebidInstances": [],
    "url": "https://u-can.jp"
  },
  {
    "libraries": [
      "googletag"
    ],
    "identitySolutions": [],
    "cdpPlatforms": [],
    "cmpInfo": {},
    "unknownAdTech": [],
    "date": "2025-07-12",
    "prebidInstances": [],
    "url": "https://zdronet.pl"
  },
  {
    "libraries": [
      "googletag"
    ],
    "identitySolutions": [],
    "cdpPlatforms": [],
    "cmpInfo": {},
    "unknownAdTech": [],
    "date": "2025-07-12",
    "prebidInstances": [],
    "url": "https://meieki.com"
  },
  {
    "libraries": [
      "googletag"
    ],
    "identitySolutions": [],
    "cdpPlatforms": [],
    "cmpInfo": {},
    "unknownAdTech": [],
    "date": "2025-07-12",
    "prebidInstances": [],
    "url": "https://forums-su.com"
  },
  {
    "libraries": [
      "googletag"
    ],
    "identitySolutions": [],
    "cdpPlatforms": [],
    "cmpInfo": {
      "ccpaApplies": true,
      "uspString": "1---"
    },
    "unknownAdTech": [],
    "date": "2025-07-12",
    "prebidInstances": [],
    "url": "https://evilbeetgossip.com"
  },
  {
    "libraries": [
      "apstag",
      "googletag"
    ],
    "identitySolutions": [],
    "cdpPlatforms": [],
    "cmpInfo": {
      "ccpaApplies": true,
      "uspString": "1YNY"
    },
    "unknownAdTech": [],
    "date": "2025-07-12",
    "prebidInstances": [
      {
        "globalVarName": "pbjs",
        "version": "v9.37.0",
        "modules": [
          "allowActivities",
          "appnexusBidAdapter",
          "connectIdSystem",
          "consentManagementUsp",
          "criteoBidAdapter",
          "criteoIdSystem",
          "dfpAdServerVideo",
          "genericAnalyticsAdapter",
          "gptPreAuction",
          "gridBidAdapter",
          "gumgumBidAdapter",
          "id5IdSystem",
          "identityLinkIdSystem",
          "pairIdSystem",
          "ixBidAdapter",
          "kargoBidAdapter",
          "merkleIdSystem",
          "nativoBidAdapter",
          "openxBidAdapter",
          "ozoneBidAdapter",
          "prebidServerBidAdapter",
          "priceFloors",
          "pubmaticBidAdapter",
          "rtbhouseBidAdapter",
          "rtdModule",
          "rubiconBidAdapter",
          "schain",
          "sharedIdSystem",
          "sharethroughBidAdapter",
          "stackadaptBidAdapter",
          "sizeMapping",
          "teadsBidAdapter",
          "tripleliftBidAdapter",
          "ttdBidAdapter",
          "undertoneBidAdapter",
          "unifiedIdSystem",
          "uid2IdSystem_shared",
          "uid2IdSystem",
          "unrulyBidAdapter",
          "userId",
          "yahooAdsBidAdapter",
          "fabrickIdSystem",
          "ftrackIdSystem",
          "33acrossIdSystem",
          "33acrossBidAdapter",
          "paapi",
          "paapiForGpt",
          "liveIntentIdSystem",
          "lotamePanoramaIdSystem",
          "lmpIdSystem",
          "linkedInAdsIdSystem",
          "currency"
        ]
      }
    ],
    "toolMetadata": {
      "prebidInitStates": {
        "pbjs": "complete"
      }
    },
    "url": "https://fresheggsdaily.com"
  },
  {
    "libraries": [
      "googletag"
    ],
    "identitySolutions": [],
    "cdpPlatforms": [],
    "cmpInfo": {},
    "unknownAdTech": [],
    "date": "2025-07-12",
    "prebidInstances": [],
    "url": "https://eloriente.net"
  },
  {
    "libraries": [
      "googletag"
    ],
    "identitySolutions": [],
    "cdpPlatforms": [],
    "cmpInfo": {
      "tcfVersion": "1.x"
    },
    "unknownAdTech": [],
    "date": "2025-07-12",
    "prebidInstances": [],
    "url": "https://contasimple.com"
  },
  {
    "libraries": [
      "Criteo"
    ],
    "identitySolutions": [],
    "cdpPlatforms": [],
    "cmpInfo": {},
    "unknownAdTech": [],
    "date": "2025-07-12",
    "prebidInstances": [],
    "url": "https://vegis.ro"
  },
  {
    "libraries": [
      "googletag"
    ],
    "identitySolutions": [],
    "cdpPlatforms": [],
    "cmpInfo": {},
    "unknownAdTech": [],
    "date": "2025-07-12",
    "prebidInstances": [],
    "url": "https://trendy-u.com"
  },
  {
    "libraries": [
      "googletag"
    ],
    "identitySolutions": [],
    "cdpPlatforms": [],
    "cmpInfo": {
      "ccpaApplies": true,
      "uspString": "1---"
    },
    "unknownAdTech": [],
    "date": "2025-07-12",
    "prebidInstances": [],
    "url": "https://damoria.de"
  },
  {
    "libraries": [
      "googletag"
    ],
    "identitySolutions": [],
    "cdpPlatforms": [],
    "cmpInfo": {},
    "unknownAdTech": [],
    "date": "2025-07-12",
    "prebidInstances": [],
    "url": "https://couponster.de"
  },
  {
    "libraries": [
      "googletag"
    ],
    "identitySolutions": [],
    "cdpPlatforms": [],
    "cmpInfo": {},
    "unknownAdTech": [],
    "date": "2025-07-12",
    "prebidInstances": [],
    "url": "https://euronogomet.com"
  },
  {
    "libraries": [
      "googletag"
    ],
    "identitySolutions": [],
    "cdpPlatforms": [],
    "cmpInfo": {},
    "unknownAdTech": [],
    "date": "2025-07-12",
    "prebidInstances": [],
    "url": "https://makerfaire.com"
  },
  {
    "libraries": [
      "googletag"
    ],
    "identitySolutions": [],
    "cdpPlatforms": [],
    "cmpInfo": {
      "tcfVersion": "2.x",
      "gdprApplies": true,
      "consentString": "CQUcHcAQUcHcAAGABCENBzFgAAAAAEPgACiQAAAUNACAFCIGgKAQECoAaAIEQAgriACAAAgAAECAAAIAAQBwAAAogJEAAAAAAAAAAABBiACAAAAAACIAIAAAAAAAAHAAAgAACAQAACAAAIggAAAABAAAAAAAAAAgAAAAAABAAAAQAQIAIBAAABAEAAAAQAAAQEAAAYAEABQAAAAAAAAAACAAAQAIAUAAAAAAAAAAAAAAAAAAACAAAAAQAAAAAAACEAcJABAbmFAIgAKgBOAFQAPQAigBeADmAIoAVwA4AB4gF-AP3AloCXgGMwOpA6oB24EOx4BEABUAJwAqAB6AEUAJwAcwBFADgAHiAX6A_YD-QJaAl4BjIDNYHUgdUA7cChpEAKACoAcAB_IEtAS9A6kDqiYAeAE4AUADgAL9AfsB_AETAJeAYyVAGgAKgBOAFQARQAtgBzAEUAOAAvwB-wETQJaAl4BjIDIC4AIAFQA4AAAA.YAAAAAAAAAAA",
      "cmpId": 6,
      "version": "1",
      "name": "Sourcepoint"
    },
    "unknownAdTech": [],
    "date": "2025-07-12",
    "prebidInstances": [
      {
        "globalVarName": "pbjsYLHH",
        "version": "v9.18.0",
        "modules": [
          "prebidCustom",
          "currency",
          "consentManagementTcf",
          "tcfControl",
          "dsaControl",
          "userId",
          "stroeerCoreBidAdapter",
          "criteoIdSystem",
          "id5IdSystem",
          "sharedIdSystem",
          "schain"
        ]
      }
    ],
    "toolMetadata": {
      "prebidInitStates": {
        "pbjsYLHH": "complete"
      }
    },
    "url": "https://zimmerschau.de"
  },
  {
    "libraries": [
      "googletag"
    ],
    "identitySolutions": [],
    "cdpPlatforms": [],
    "cmpInfo": {
      "name": "OneTrust",
      "gdprApplies": false
    },
    "unknownAdTech": [],
    "date": "2025-07-12",
    "prebidInstances": [],
    "url": "https://searshometownstores.com"
  },
  {
    "libraries": [
      "googletag"
    ],
    "identitySolutions": [],
    "cdpPlatforms": [],
    "cmpInfo": {},
    "unknownAdTech": [],
    "date": "2025-07-12",
    "prebidInstances": [],
    "url": "https://bizmanualz.com"
  },
  {
    "libraries": [
      "googletag"
    ],
    "identitySolutions": [],
    "cdpPlatforms": [],
    "cmpInfo": {},
    "unknownAdTech": [],
    "date": "2025-07-12",
    "prebidInstances": [],
    "url": "https://zooland.ro"
  },
  {
    "libraries": [
      "apstag",
      "googletag",
      "Criteo"
    ],
    "identitySolutions": [
      "UID2.0",
      "ID5"
    ],
    "cdpPlatforms": [
      "Segment"
    ],
    "cmpInfo": {
      "ccpaApplies": true,
      "uspString": "1YNN"
    },
    "unknownAdTech": [],
    "date": "2025-07-12",
    "prebidInstances": [
      {
        "globalVarName": "$$PREBID_GLOBAL$$",
        "version": "v$prebid.version$",
        "modules": [
          "v$prebid.modulesList$"
        ]
      },
      {
        "globalVarName": "owpbjs",
        "version": "v6.18.0",
        "modules": [
          "33acrossIdSystem",
          "consentManagement",
          "consentManagementUsp",
          "criteoIdSystem",
          "id5IdSystem",
          "identityLinkIdSystem",
          "lotamePanoramaIdSystem",
          "parrableIdSystem",
          "unifiedIdSystem",
          "userId"
        ]
      }
    ],
    "toolMetadata": {
      "prebidInitStates": {
        "$$PREBID_GLOBAL$$": "complete",
        "owpbjs": "complete"
      }
    },
    "url": "https://kdminer.com"
  },
  {
    "libraries": [
      "googletag"
    ],
    "identitySolutions": [],
    "cdpPlatforms": [],
    "cmpInfo": {},
    "unknownAdTech": [],
    "date": "2025-07-12",
    "prebidInstances": [],
    "url": "https://sgoliver.net"
  },
  {
    "libraries": [
      "apstag",
      "googletag"
    ],
    "identitySolutions": [],
    "cdpPlatforms": [],
    "cmpInfo": {
      "ccpaApplies": true,
      "uspString": "1YNY"
    },
    "unknownAdTech": [],
    "date": "2025-07-12",
    "prebidInstances": [
      {
        "globalVarName": "pbjs",
        "version": "v9.37.0",
        "modules": [
          "allowActivities",
          "appnexusBidAdapter",
          "connectIdSystem",
          "consentManagementUsp",
          "criteoBidAdapter",
          "criteoIdSystem",
          "dfpAdServerVideo",
          "genericAnalyticsAdapter",
          "gptPreAuction",
          "gridBidAdapter",
          "gumgumBidAdapter",
          "id5IdSystem",
          "identityLinkIdSystem",
          "pairIdSystem",
          "ixBidAdapter",
          "kargoBidAdapter",
          "merkleIdSystem",
          "nativoBidAdapter",
          "openxBidAdapter",
          "ozoneBidAdapter",
          "prebidServerBidAdapter",
          "priceFloors",
          "pubmaticBidAdapter",
          "rtbhouseBidAdapter",
          "rtdModule",
          "rubiconBidAdapter",
          "schain",
          "sharedIdSystem",
          "sharethroughBidAdapter",
          "stackadaptBidAdapter",
          "sizeMapping",
          "teadsBidAdapter",
          "tripleliftBidAdapter",
          "ttdBidAdapter",
          "undertoneBidAdapter",
          "unifiedIdSystem",
          "uid2IdSystem_shared",
          "uid2IdSystem",
          "unrulyBidAdapter",
          "userId",
          "yahooAdsBidAdapter",
          "fabrickIdSystem",
          "ftrackIdSystem",
          "33acrossIdSystem",
          "33acrossBidAdapter",
          "paapi",
          "paapiForGpt",
          "liveIntentIdSystem",
          "lotamePanoramaIdSystem",
          "lmpIdSystem",
          "linkedInAdsIdSystem",
          "currency"
        ]
      }
    ],
    "toolMetadata": {
      "prebidInitStates": {
        "pbjs": "complete"
      }
    },
    "url": "https://gopherhole.com"
  },
  {
    "libraries": [
      "googletag"
    ],
    "identitySolutions": [],
    "cdpPlatforms": [],
    "cmpInfo": {},
    "unknownAdTech": [],
    "date": "2025-07-12",
    "prebidInstances": [],
    "url": "https://iso1200.com"
  },
  {
    "libraries": [
      "googletag"
    ],
    "identitySolutions": [],
    "cdpPlatforms": [],
    "cmpInfo": {},
    "unknownAdTech": [],
    "date": "2025-07-12",
    "prebidInstances": [],
    "url": "https://skitarrate.it"
  },
  {
    "libraries": [
      "googletag"
    ],
    "identitySolutions": [],
    "cdpPlatforms": [],
    "cmpInfo": {},
    "unknownAdTech": [],
    "date": "2025-07-12",
    "prebidInstances": [],
    "url": "https://ashvamegh.net"
  },
  {
    "libraries": [
      "googletag"
    ],
    "identitySolutions": [],
    "cdpPlatforms": [],
    "cmpInfo": {},
    "unknownAdTech": [],
    "date": "2025-07-12",
    "prebidInstances": [],
    "url": "https://ilioupoligiaolous.gr"
  },
  {
    "libraries": [
      "googletag"
    ],
    "identitySolutions": [],
    "cdpPlatforms": [],
    "cmpInfo": {},
    "unknownAdTech": [],
    "date": "2025-07-12",
    "prebidInstances": [],
    "url": "https://aprireinfranchising.it"
  },
  {
    "libraries": [
      "googletag"
    ],
    "identitySolutions": [],
    "cdpPlatforms": [],
    "cmpInfo": {},
    "unknownAdTech": [],
    "date": "2025-07-12",
    "prebidInstances": [],
    "url": "https://salzi.at"
  },
  {
    "libraries": [
      "googletag"
    ],
    "identitySolutions": [],
    "cdpPlatforms": [],
    "cmpInfo": {
      "tcfVersion": "2.x",
      "gdprApplies": true,
      "consentString": "CQUcHcAQUcHcAAHABBENBrFgAAAAAAAAAAAAAAAAAADEoAMAAQWbKQAYAAgs2OgAwABBZshABgACCzYSADAAEFmy0AGAAILNgAAA.YAAAAAAAAAAA",
      "cmpId": 7,
      "version": "1",
      "name": "Didomi"
    },
    "unknownAdTech": [],
    "date": "2025-07-12",
    "prebidInstances": [],
    "url": "https://columbusmagazine.nl"
  },
  {
    "libraries": [
      "googletag"
    ],
    "identitySolutions": [],
    "cdpPlatforms": [],
    "cmpInfo": {},
    "unknownAdTech": [],
    "date": "2025-07-12",
    "prebidInstances": [],
    "url": "https://altenergymag.com"
  },
  {
    "libraries": [
      "googletag"
    ],
    "identitySolutions": [
      "ID5"
    ],
    "cdpPlatforms": [],
    "cmpInfo": {},
    "unknownAdTech": [],
    "date": "2025-07-12",
    "prebidInstances": [
      {
        "globalVarName": "tmzr",
        "version": "v9.16.0",
        "modules": [
          "33acrossIdSystem",
          "adagioAnalyticsAdapter",
          "adagioBidAdapter",
          "adagioRtdProvider",
          "amxBidAdapter",
          "appnexusBidAdapter",
          "consentManagementTcf",
          "criteoBidAdapter",
          "criteoIdSystem",
          "currency",
          "eplanningBidAdapter",
          "fpdModule",
          "id5IdSystem",
          "justpremiumBidAdapter",
          "lotamePanoramaIdSystem",
          "moneytizerBidAdapter",
          "nativeRendering",
          "onetagBidAdapter",
          "openxBidAdapter",
          "outbrainBidAdapter",
          "prebidServerBidAdapter",
          "priceFloors",
          "pubProvidedIdSystem",
          "quantcastIdSystem",
          "rtbhouseBidAdapter",
          "rtdModule",
          "rubiconBidAdapter",
          "schain",
          "sharedIdSystem",
          "sharethroughBidAdapter",
          "sirdataRtdProvider",
          "smilewantedBidAdapter",
          "sovrnBidAdapter",
          "themoneytizerBidAdapter",
          "topicsFpdModule",
          "tripleliftBidAdapter",
          "userId"
        ]
      }
    ],
    "toolMetadata": {
      "prebidInitStates": {
        "tmzr": "complete"
      }
    },
    "url": "https://quimicayalgomas.com"
  },
  {
    "libraries": [
      "googletag"
    ],
    "identitySolutions": [],
    "cdpPlatforms": [],
    "cmpInfo": {},
    "unknownAdTech": [],
    "date": "2025-07-12",
    "prebidInstances": [],
    "url": "https://yellow-bricks.com"
  },
  {
    "libraries": [
      "googletag"
    ],
    "identitySolutions": [],
    "cdpPlatforms": [],
    "cmpInfo": {},
    "unknownAdTech": [],
    "date": "2025-07-12",
    "prebidInstances": [],
    "url": "https://gogagah.com"
  },
  {
    "libraries": [
      "googletag"
    ],
    "identitySolutions": [],
    "cdpPlatforms": [],
    "cmpInfo": {
      "tcfVersion": "2.x",
      "gdprApplies": false,
      "cmpId": 10,
      "version": "56",
      "ccpaApplies": true,
      "uspString": "1---"
    },
    "unknownAdTech": [],
    "date": "2025-07-12",
    "prebidInstances": [],
    "url": "https://businesscommunity.it"
  },
  {
    "libraries": [
      "googletag"
    ],
    "identitySolutions": [],
    "cdpPlatforms": [],
    "cmpInfo": {},
    "unknownAdTech": [],
    "date": "2025-07-12",
    "prebidInstances": [],
    "url": "https://tradecounterdirect.com"
  },
  {
    "libraries": [
      "googletag"
    ],
    "identitySolutions": [],
    "cdpPlatforms": [],
    "cmpInfo": {},
    "unknownAdTech": [],
    "date": "2025-07-12",
    "prebidInstances": [],
    "url": "https://expectaculos.com"
  },
  {
    "libraries": [
      "googletag"
    ],
    "identitySolutions": [],
    "cdpPlatforms": [],
    "cmpInfo": {
      "tcfVersion": "2.x",
      "gdprApplies": true,
      "consentString": "CQUcHcAQUcHcAB7FmBITBzFsAP_gAAAgAAAALYNT_G__bXlr-b736ftkeYxf9_hr7sQxBgbJk24FzLvW_JwW32E7NAzatqYKmRIAu3TBIQNlHJDURVCgKogVrzDMaEyUoTtKJ6BkiFMRY2JYCFxvm4tjeQCY5vr991d9mR-t7dr83dzyy4hnv3a9_-S1WJCdIYetDfv8ZBKT-9IE9_x8v4v4_N7pE2-eS1n_tGvp6D9-Yvv_dB399_bbffzPn__rl_e_X__f_n37v943X77_____fBa2B-ADUAHAAQwBgADLAGaAO4AjgBegDPgH2AQfAjwCPQEqgJiATaAoeBTQFNgKsAXAAuwBfoDIQGZgNGAamA3QBywDtgHjgPPAgIBBQCHoEaQJEASUAlGBMmCZgJmgTYgm4CboE5gJ3ATwAn6BRYCjIFHAKSAUuAqUBVICrIFYAK4AVzAr6BYWCxILFAWeAtWBa0AUJBwAAXABQAFQAOAAeABAAC-AGQAagA8ACGAEwAKoAbwA_ACEgEMARIAjgBNACtAGAAMOAZQBlgDZAHPAO4A74B7AHxAPsA_QCAAEUgIuAjEBGgEcgJEAk0BPwFBgKgAq4BcwC9AGKANEAbQA3ABxAD2gIdgR6BIoCdgFDgKPAUiApsBbAC4AFyALsAXeAvMBhsDIwMkAZOAy4BmYDOYGrgayA2MBtADbwG5gN1AcmA5cB44D4wH_AQEAgmBBgCEMELQQvgh6CH4EfQJFQSYBJkCWYEtwJfATAgmWCZgEzgJqgTYAm4BOYCdIE7gJ4QUHBQgChYFFQKSgUuApkBTwCoAFRgKlAVOAq6BWwCt4FfALCgWOAsrBawFrR0IMABcAFAAVAA4ACCAFwAXwAyADUAHgATAApgBVgC4ALoAYgA3gB-gEMARIAjgBNACcAFGAK0AYAAwwBlADRAGyAOeAdwB3wD2APiAfYB-wEUARiAjgCTQE_AUGAqICrgFiALnAXkBegDFAG0ANxAcQBxgD2gH2AQgAh0BE4CL4EegSKAmQBOwCh4FHgUgApOBTQFNgKsAWKAtgBboC4AFyQLsAu0Bd4C8wF9AMNAY9AyMDJAGTgMqgZYBlwDMwGcgNNAarA1cDWAG0ANvAbqA4sByYDlwHjgPjAfWA-4B_YD_gIAgQEAgwBC0CHoEdgI-gSEAkUBJkCVcEswS0Al0BL4CYEEywTMAmcBNUCbAE3AJvAThAnMBOmCdoJ3ATwAnmBQYChAFCwKJAUVApKBS4CngFRgKlAVOgq4CroFbAK3gWDAsmBZWC1gLWkIHgACwAKAAuABqAFUALgAYgA3gB-AGAAOeAdwB3gEUAI4ASkAoMBUQFXALmAYoA2gBxgEOgInAR6ApOBTQFNgKsAWKAtEBcAC5AF2AMjAZOAzkBqoDxwHxgP7AgIBBgCFoEPQJCASKAl0BM4CbAE5gJ3ATwAnmBQYCioFJQKXAVKAq-BYIC1pKCUAAsACgAHAAeABDACYAFUALgAYoBDAESAI4AUYArQBgADZAHeAPwAjkBUQFXALmAYoA4gCEAEOgIvgR6BIoCjwFJwKaApsBYoC2AF2ALzgZGBkgDJwGWAM5AawA28B8YEAQICAQPAgwBCECHoEfQJFASVAlWBLoCX0EywTMAmcBNUCbgE4QJzQTtBO4CeAE8wKKgUlApcBUYCpQFTgK2AVvgsECwYFiwLKgWegtYC1pSDYAAuACgAKgAcABBADIANAAeABDACYAFUAMQAfoBDAESAI4AUYArQBgADKAGiANkAc4A74B9gH6ARYAjEBHAElAKDAVEBVwC5gF5AMUAbQA3EBxAHGAPaAfYBDoCJwEXwI9AkUBOwChwFIAKTgU0BTYCrAFigLYAXAAuSBdgF2gLzAX0Aw2BkYGSAMngZYBlwDOYGsAayA28BuoDkwHigPHAfGA_sB_wEBAIJgQYAhCBC0CGYEOQI7AR9AkVBJgEmQJVgSzAl0BL4CYEEywTMAmcBNUCbAE3gJzQTtBO4CeAE8wKFgUVApKBS4CngFRgKlAVOArYBW8CwQFhQLFgWTAsqBZ6C1gLWgAA",
      "cmpId": 123,
      "version": "358"
    },
    "unknownAdTech": [],
    "date": "2025-07-12",
    "prebidInstances": [],
    "url": "https://cagliaripad.it"
  },
  {
    "libraries": [
      "apstag",
      "googletag"
    ],
    "identitySolutions": [],
    "cdpPlatforms": [],
    "cmpInfo": {
      "ccpaApplies": true,
      "uspString": "1YNY"
    },
    "unknownAdTech": [],
    "date": "2025-07-12",
    "prebidInstances": [
      {
        "globalVarName": "pbjs",
        "version": "v9.37.0",
        "modules": [
          "allowActivities",
          "appnexusBidAdapter",
          "connectIdSystem",
          "consentManagementUsp",
          "criteoBidAdapter",
          "criteoIdSystem",
          "dfpAdServerVideo",
          "genericAnalyticsAdapter",
          "gptPreAuction",
          "gridBidAdapter",
          "gumgumBidAdapter",
          "id5IdSystem",
          "identityLinkIdSystem",
          "pairIdSystem",
          "ixBidAdapter",
          "kargoBidAdapter",
          "merkleIdSystem",
          "nativoBidAdapter",
          "openxBidAdapter",
          "ozoneBidAdapter",
          "prebidServerBidAdapter",
          "priceFloors",
          "pubmaticBidAdapter",
          "rtbhouseBidAdapter",
          "rtdModule",
          "rubiconBidAdapter",
          "schain",
          "sharedIdSystem",
          "sharethroughBidAdapter",
          "stackadaptBidAdapter",
          "sizeMapping",
          "teadsBidAdapter",
          "tripleliftBidAdapter",
          "ttdBidAdapter",
          "undertoneBidAdapter",
          "unifiedIdSystem",
          "uid2IdSystem_shared",
          "uid2IdSystem",
          "unrulyBidAdapter",
          "userId",
          "yahooAdsBidAdapter",
          "fabrickIdSystem",
          "ftrackIdSystem",
          "33acrossIdSystem",
          "33acrossBidAdapter",
          "paapi",
          "paapiForGpt",
          "liveIntentIdSystem",
          "lotamePanoramaIdSystem",
          "lmpIdSystem",
          "linkedInAdsIdSystem",
          "currency"
        ]
      }
    ],
    "toolMetadata": {
      "prebidInitStates": {
        "pbjs": "complete"
      }
    },
    "url": "https://due.com"
  },
  {
    "libraries": [
      "googletag"
    ],
    "identitySolutions": [],
    "cdpPlatforms": [],
    "cmpInfo": {
      "tcfVersion": "2.x",
      "gdprApplies": true,
      "consentString": "CQUc8LAQUc8LAAfU1CFRBzFgAAAAAAAAAAQ4AAABNgBAA4ACaAAA",
      "cmpId": 31,
      "version": "1333"
    },
    "unknownAdTech": [],
    "date": "2025-07-12",
    "prebidInstances": [
      {
        "globalVarName": "htagpbjs",
        "version": "v9.53.1",
        "modules": [
          "prebidServerBidAdapter",
          "consentManagementGpp",
          "consentManagementTcf",
          "consentManagementUsp",
          "gppControl_usnat",
          "gppControl_usstates",
          "gptPreAuction",
          "schain",
          "priceFloors",
          "currency",
          "rtdModule",
          "adagioRtdProvider",
          "paapi",
          "userId",
          "sharedIdSystem",
          "criteoIdSystem",
          "teadsIdSystem",
          "unifiedIdSystem",
          "amxIdSystem",
          "oneIdIdSystem",
          "adfBidAdapter",
          "connectadBidAdapter",
          "smilewantedBidAdapter",
          "appnexusBidAdapter",
          "pubmaticBidAdapter",
          "rubiconBidAdapter",
          "xandrBidAdapter",
          "teadsBidAdapter",
          "smartadserverBidAdapter",
          "ixBidAdapter"
        ]
      }
    ],
    "toolMetadata": {
      "prebidInitStates": {
        "htagpbjs": "complete"
      }
    },
    "url": "https://lenouvelliste.ch"
  },
  {
    "libraries": [
      "googletag"
    ],
    "identitySolutions": [],
    "cdpPlatforms": [],
    "cmpInfo": {
      "ccpaApplies": true,
      "uspString": "1---",
      "name": "Cookiebot",
      "consentString": "0"
    },
    "unknownAdTech": [],
    "date": "2025-07-12",
    "prebidInstances": [],
    "url": "https://ksc.de"
  },
  {
    "libraries": [
      "googletag"
    ],
    "identitySolutions": [],
    "cdpPlatforms": [],
    "cmpInfo": {},
    "unknownAdTech": [],
    "date": "2025-07-12",
    "prebidInstances": [],
    "url": "https://scrigroup.com"
  },
  {
    "libraries": [
      "apstag",
      "googletag",
      "ats"
    ],
    "identitySolutions": [],
    "cdpPlatforms": [],
    "cmpInfo": {
      "ccpaApplies": true,
      "uspString": "1YNY"
    },
    "unknownAdTech": [],
    "date": "2025-07-12",
    "prebidInstances": [
      {
        "globalVarName": "pbjs",
        "version": "v9.37.0",
        "modules": [
          "allowActivities",
          "appnexusBidAdapter",
          "connectIdSystem",
          "consentManagementUsp",
          "criteoBidAdapter",
          "criteoIdSystem",
          "dfpAdServerVideo",
          "genericAnalyticsAdapter",
          "gptPreAuction",
          "gridBidAdapter",
          "gumgumBidAdapter",
          "id5IdSystem",
          "identityLinkIdSystem",
          "pairIdSystem",
          "ixBidAdapter",
          "kargoBidAdapter",
          "merkleIdSystem",
          "nativoBidAdapter",
          "openxBidAdapter",
          "ozoneBidAdapter",
          "prebidServerBidAdapter",
          "priceFloors",
          "pubmaticBidAdapter",
          "rtbhouseBidAdapter",
          "rtdModule",
          "rubiconBidAdapter",
          "schain",
          "sharedIdSystem",
          "sharethroughBidAdapter",
          "stackadaptBidAdapter",
          "sizeMapping",
          "teadsBidAdapter",
          "tripleliftBidAdapter",
          "ttdBidAdapter",
          "undertoneBidAdapter",
          "unifiedIdSystem",
          "uid2IdSystem_shared",
          "uid2IdSystem",
          "unrulyBidAdapter",
          "userId",
          "yahooAdsBidAdapter",
          "fabrickIdSystem",
          "ftrackIdSystem",
          "33acrossIdSystem",
          "33acrossBidAdapter",
          "paapi",
          "paapiForGpt",
          "liveIntentIdSystem",
          "lotamePanoramaIdSystem",
          "lmpIdSystem",
          "linkedInAdsIdSystem",
          "currency"
        ]
      }
    ],
    "toolMetadata": {
      "prebidInitStates": {
        "pbjs": "complete"
      }
    },
    "url": "https://eleganceandenchantment.com"
  },
  {
    "libraries": [
      "googletag"
    ],
    "identitySolutions": [],
    "cdpPlatforms": [],
    "cmpInfo": {},
    "unknownAdTech": [],
    "date": "2025-07-12",
    "prebidInstances": [],
    "url": "https://usb-drivers.org"
  },
  {
    "libraries": [
      "apstag",
      "googletag"
    ],
    "identitySolutions": [
      "ID5"
    ],
    "cdpPlatforms": [],
    "cmpInfo": {
      "tcfVersion": "2.x",
      "gdprApplies": false,
      "cmpId": 10,
      "version": "53",
      "ccpaApplies": true,
      "uspString": "1---"
    },
    "unknownAdTech": [],
    "date": "2025-07-12",
    "prebidInstances": [
      {
        "globalVarName": "fsprebid",
        "version": "v9.44.1",
        "modules": [
          "33acrossBidAdapter",
          "33acrossIdSystem",
          "appnexusBidAdapter",
          "carbonAnalyticsAdapter",
          "connectIdSystem",
          "consentManagementGpp",
          "consentManagementTcf",
          "consentManagementUsp",
          "criteoBidAdapter",
          "criteoIdSystem",
          "dfpAdServerVideo",
          "fabrickIdSystem",
          "fpdModule",
          "gameraRtdProvider",
          "gptPreAuction",
          "gridBidAdapter",
          "gumgumBidAdapter",
          "hadronIdSystem",
          "hadronRtdProvider",
          "id5IdSystem",
          "identityLinkIdSystem",
          "insticatorBidAdapter",
          "ixBidAdapter",
          "liveIntentIdSystem",
          "medianetBidAdapter",
          "prebidServerBidAdapter",
          "priceFloors",
          "pubProvidedIdSystem",
          "pubmaticBidAdapter",
          "riseBidAdapter",
          "rtdModule",
          "rubiconBidAdapter",
          "schain",
          "sharethroughBidAdapter",
          "sizeMappingV2",
          "sovrnBidAdapter",
          "topicsFpdModule",
          "tripleliftBidAdapter",
          "ttdBidAdapter",
          "uid2IdSystem",
          "unifiedIdSystem",
          "userId",
          "videoModule",
          "videojsVideoProvider",
          "yieldmoBidAdapter"
        ]
      }
    ],
    "toolMetadata": {
      "prebidInitStates": {
        "fsprebid": "complete"
      }
    },
    "url": "https://iron-start.com"
  },
  {
    "libraries": [
      "googletag"
    ],
    "identitySolutions": [],
    "cdpPlatforms": [],
    "cmpInfo": {},
    "unknownAdTech": [],
    "date": "2025-07-12",
    "prebidInstances": [],
    "url": "https://fireflycarrental.com"
  },
  {
    "libraries": [
      "googletag"
    ],
    "identitySolutions": [
      "ID5"
    ],
    "cdpPlatforms": [],
    "cmpInfo": {},
    "unknownAdTech": [],
    "date": "2025-07-12",
    "prebidInstances": [
      {
        "globalVarName": "tmzr",
        "version": "v9.39.0",
        "modules": [
          "33acrossIdSystem",
          "adagioAnalyticsAdapter",
          "adagioBidAdapter",
          "adagioRtdProvider",
          "adyoulikeBidAdapter",
          "amxIdSystem",
          "appnexusBidAdapter",
          "betweenBidAdapter",
          "criteoIdSystem",
          "currency",
          "eplanningBidAdapter",
          "fpdModule",
          "id5IdSystem",
          "justpremiumBidAdapter",
          "lotamePanoramaIdSystem",
          "moneytizerBidAdapter",
          "nativeRendering",
          "onetagBidAdapter",
          "prebidServerBidAdapter",
          "priceFloors",
          "pubProvidedIdSystem",
          "pubxaiAnalyticsAdapter",
          "quantcastIdSystem",
          "richaudienceBidAdapter",
          "rtdModule",
          "schain",
          "sharedIdSystem",
          "sharethroughBidAdapter",
          "smilewantedBidAdapter",
          "sovrnBidAdapter",
          "themoneytizerBidAdapter",
          "topicsFpdModule",
          "userId"
        ]
      }
    ],
    "toolMetadata": {
      "prebidInitStates": {
        "tmzr": "complete"
      }
    },
    "url": "https://ilcittadinoonline.it"
  },
  {
    "libraries": [
      "googletag"
    ],
    "identitySolutions": [],
    "cdpPlatforms": [],
    "cmpInfo": {},
    "unknownAdTech": [],
    "date": "2025-07-12",
    "prebidInstances": [],
    "url": "https://talkop.com"
  },
  {
    "libraries": [
      "googletag",
      "Criteo"
    ],
    "identitySolutions": [
      "UID2.0"
    ],
    "cdpPlatforms": [],
    "cmpInfo": {
      "tcfVersion": "2.x",
      "gdprApplies": true,
      "consentString": "",
      "cmpId": 10,
      "version": "60",
      "ccpaApplies": true,
      "uspString": "1---"
    },
    "unknownAdTech": [],
    "date": "2025-07-12",
    "prebidInstances": [
      {
        "globalVarName": "pbjs_hbagencyicd",
        "version": "v9.52.0",
        "modules": [
          "adagioAnalyticsAdapter",
          "adagioBidAdapter",
          "adagioRtdProvider",
          "adfBidAdapter",
          "admaticBidAdapter",
          "adtelligentBidAdapter",
          "adyoulikeBidAdapter",
          "amxBidAdapter",
          "amxIdSystem",
          "appnexusBidAdapter",
          "bidViewabilityIO",
          "consentManagementTcf",
          "criteoBidAdapter",
          "criteoIdSystem",
          "currency",
          "e_volutionBidAdapter",
          "equativBidAdapter",
          "genericAnalyticsAdapter",
          "geoedgeRtdProvider",
          "gumgumBidAdapter",
          "id5IdSystem",
          "improvedigitalBidAdapter",
          "invibesBidAdapter",
          "kueezRtbBidAdapter",
          "lotamePanoramaIdSystem",
          "multibid",
          "nativeRendering",
          "oguryBidAdapter",
          "onetagBidAdapter",
          "priceFloors",
          "pubmaticBidAdapter",
          "quantcastIdSystem",
          "richaudienceBidAdapter",
          "rtdModule",
          "rubiconBidAdapter",
          "schain",
          "sharedIdSystem",
          "sharethroughBidAdapter",
          "smartadserverBidAdapter",
          "smilewantedBidAdapter",
          "sovrnBidAdapter",
          "sparteoBidAdapter",
          "tcfControl",
          "teadsBidAdapter",
          "teadsIdSystem",
          "timeoutRtdProvider",
          "tripleliftBidAdapter",
          "unrulyBidAdapter",
          "userId"
        ]
      }
    ],
    "toolMetadata": {
      "prebidInitStates": {
        "pbjs_hbagencyicd": "complete"
      }
    },
    "url": "https://ilcaffe.tv"
  },
  {
    "libraries": [
      "googletag"
    ],
    "identitySolutions": [],
    "cdpPlatforms": [],
    "cmpInfo": {},
    "unknownAdTech": [],
    "date": "2025-07-12",
    "prebidInstances": [],
    "url": "https://watismijnip.nl"
  },
  {
    "libraries": [
      "googletag",
      "Criteo"
    ],
    "identitySolutions": [],
    "cdpPlatforms": [],
    "cmpInfo": {},
    "unknownAdTech": [],
    "date": "2025-07-12",
    "prebidInstances": [
      {
        "globalVarName": "bxpbjs",
        "version": "v9.49.1",
        "modules": [
          "33acrossAnalyticsAdapter",
          "33acrossBidAdapter",
          "adagioAnalyticsAdapter",
          "adagioBidAdapter",
          "adagioRtdProvider",
          "adkernelAdnAnalyticsAdapter",
          "adkernelBidAdapter",
          "adpod",
          "adtelligentBidAdapter",
          "adyoulikeBidAdapter",
          "amxBidAdapter",
          "appnexusBidAdapter",
          "betweenBidAdapter",
          "colossussspBidAdapter",
          "consentManagementGpp",
          "consentManagementUsp",
          "criteoBidAdapter",
          "currency",
          "eplanningBidAdapter",
          "geolocationRtdProvider",
          "gppControl_usnat",
          "gppControl_usstates",
          "gptPreAuction",
          "inmobiBidAdapter",
          "instreamTracking",
          "ixBidAdapter",
          "krushmediaBidAdapter",
          "kueezRtbBidAdapter",
          "limelightDigitalBidAdapter",
          "nobidAnalyticsAdapter",
          "nobidBidAdapter",
          "onetagBidAdapter",
          "openxBidAdapter",
          "pixfutureBidAdapter",
          "priceFloors",
          "pubmaticAnalyticsAdapter",
          "pubmaticBidAdapter",
          "richaudienceBidAdapter",
          "riseBidAdapter",
          "rtbhouseBidAdapter",
          "rtdModule",
          "rubiconBidAdapter",
          "schain",
          "seedtagBidAdapter",
          "smartadserverBidAdapter",
          "smarthubBidAdapter",
          "smilewantedBidAdapter",
          "sovrnBidAdapter",
          "teadsBidAdapter",
          "timeoutRtdProvider",
          "unrulyBidAdapter",
          "videoModule",
          "videojsVideoProvider",
          "vidoomyBidAdapter",
          "yandexAnalyticsAdapter",
          "yandexBidAdapter"
        ]
      }
    ],
    "toolMetadata": {
      "prebidInitStates": {
        "bxpbjs": "complete"
      }
    },
    "url": "https://elempresario.mx"
  },
  {
    "libraries": [
      "googletag"
    ],
    "identitySolutions": [],
    "cdpPlatforms": [],
    "cmpInfo": {},
    "unknownAdTech": [],
    "date": "2025-07-12",
    "prebidInstances": [],
    "url": "https://genkienglish.net"
  },
  {
    "libraries": [
      "googletag"
    ],
    "identitySolutions": [],
    "cdpPlatforms": [],
    "cmpInfo": {},
    "unknownAdTech": [],
    "date": "2025-07-12",
    "prebidInstances": [],
    "url": "https://abgne.tw"
  },
  {
    "libraries": [
      "googletag"
    ],
    "identitySolutions": [],
    "cdpPlatforms": [],
    "cmpInfo": {},
    "unknownAdTech": [],
    "date": "2025-07-12",
    "prebidInstances": [],
    "url": "https://cindabella.com"
  },
  {
    "libraries": [
      "googletag"
    ],
    "identitySolutions": [],
    "cdpPlatforms": [],
    "cmpInfo": {},
    "unknownAdTech": [],
    "date": "2025-07-12",
    "prebidInstances": [],
    "url": "https://izmirliyiz.com"
  },
  {
    "libraries": [
      "googletag"
    ],
    "identitySolutions": [],
    "cdpPlatforms": [],
    "cmpInfo": {},
    "unknownAdTech": [],
    "date": "2025-07-12",
    "prebidInstances": [],
    "url": "https://dichvudidong.vn"
  },
  {
    "libraries": [
      "googletag"
    ],
    "identitySolutions": [],
    "cdpPlatforms": [],
    "cmpInfo": {},
    "unknownAdTech": [],
    "date": "2025-07-12",
    "prebidInstances": [],
    "url": "https://collegeatlas.org"
  },
  {
    "libraries": [
      "googletag"
    ],
    "identitySolutions": [],
    "cdpPlatforms": [],
    "cmpInfo": {},
    "unknownAdTech": [],
    "date": "2025-07-12",
    "prebidInstances": [],
    "url": "https://gp1.hr"
  },
  {
    "libraries": [
      "googletag"
    ],
    "identitySolutions": [],
    "cdpPlatforms": [],
    "cmpInfo": {},
    "unknownAdTech": [],
    "date": "2025-07-12",
    "prebidInstances": [],
    "url": "https://gokeyless.com"
  },
  {
    "libraries": [
      "googletag"
    ],
    "identitySolutions": [],
    "cdpPlatforms": [],
    "cmpInfo": {},
    "unknownAdTech": [],
    "date": "2025-07-12",
    "prebidInstances": [],
    "url": "https://gamesumo.com"
  },
  {
    "libraries": [
      "Criteo"
    ],
    "identitySolutions": [],
    "cdpPlatforms": [],
    "cmpInfo": {},
    "unknownAdTech": [],
    "date": "2025-07-12",
    "prebidInstances": [],
    "url": "https://merongshop.com"
  },
  {
    "libraries": [
      "apstag",
      "googletag",
      "Criteo"
    ],
    "identitySolutions": [
      "UID2.0",
      "ID5"
    ],
    "cdpPlatforms": [],
    "cmpInfo": {},
    "unknownAdTech": [],
    "date": "2025-07-12",
    "prebidInstances": [
      {
        "globalVarName": "stpd",
        "version": "v4.21.0-pre",
        "modules": []
      }
    ],
    "toolMetadata": {
      "prebidInitStates": {
        "stpd": "partial"
      }
    },
    "url": "https://mojekrpice.rs"
  },
  {
    "libraries": [
      "googletag"
    ],
    "identitySolutions": [],
    "cdpPlatforms": [],
    "cmpInfo": {
      "tcfVersion": "2.x",
      "gdprApplies": false,
      "cmpId": 10,
      "version": "56",
      "ccpaApplies": true,
      "uspString": "1---"
    },
    "unknownAdTech": [],
    "date": "2025-07-12",
    "prebidInstances": [
      {
        "globalVarName": "qpb",
        "version": "v9.23.0",
        "modules": [
          "adagioBidAdapter",
          "adagioRtdProvider",
          "adfBidAdapter",
          "adheseBidAdapter",
          "amxBidAdapter",
          "appnexusBidAdapter",
          "consentManagementTcf",
          "consentManagementUsp",
          "criteoBidAdapter",
          "criteoIdSystem",
          "currency",
          "dfpAdServerVideo",
          "dsaControl",
          "dspxBidAdapter",
          "freewheel-sspBidAdapter",
          "id5IdSystem",
          "identityLinkIdSystem",
          "impactifyBidAdapter",
          "improvedigitalBidAdapter",
          "instreamTracking",
          "invibesBidAdapter",
          "ixBidAdapter",
          "kueezRtbBidAdapter",
          "liveIntentIdSystem",
          "lotamePanoramaIdSystem",
          "netIdSystem",
          "nexx360BidAdapter",
          "oguryBidAdapter",
          "priceFloors",
          "pubmaticBidAdapter",
          "pubxaiAnalyticsAdapter",
          "pubxaiRtdProvider",
          "r2b2BidAdapter",
          "richaudienceBidAdapter",
          "rtdModule",
          "rubiconBidAdapter",
          "schain",
          "seedtagBidAdapter",
          "sharedIdSystem",
          "sharethroughBidAdapter",
          "showheroes-bsBidAdapter",
          "smartadserverBidAdapter",
          "smartxBidAdapter",
          "smilewantedBidAdapter",
          "sovrnBidAdapter",
          "sparteoBidAdapter",
          "stroeerCoreBidAdapter",
          "stvBidAdapter",
          "targetVideoBidAdapter",
          "teadsBidAdapter",
          "teadsIdSystem",
          "tripleliftBidAdapter",
          "unifiedIdSystem",
          "unrulyBidAdapter",
          "userId",
          "utiqIdSystem",
          "utiqMtpIdSystem",
          "vidoomyBidAdapter",
          "visxBidAdapter",
          "vlybyAnalyticsAdapter",
          "yieldlabBidAdapter"
        ]
      },
      {
        "globalVarName": "tmzr",
        "version": "v9.39.0",
        "modules": [
          "33acrossIdSystem",
          "adagioAnalyticsAdapter",
          "adagioBidAdapter",
          "adagioRtdProvider",
          "adfBidAdapter",
          "adtelligentBidAdapter",
          "amxBidAdapter",
          "amxIdSystem",
          "appnexusBidAdapter",
          "azerionedgeRtdProvider",
          "consentManagementTcf",
          "criteoBidAdapter",
          "criteoIdSystem",
          "currency",
          "eplanningBidAdapter",
          "fpdModule",
          "gumgumBidAdapter",
          "id5IdSystem",
          "improvedigitalBidAdapter",
          "justpremiumBidAdapter",
          "kueezRtbBidAdapter",
          "lotamePanoramaIdSystem",
          "medianetBidAdapter",
          "missenaBidAdapter",
          "moneytizerBidAdapter",
          "nativeRendering",
          "oguryBidAdapter",
          "onetagBidAdapter",
          "openxBidAdapter",
          "outbrainBidAdapter",
          "prebidServerBidAdapter",
          "priceFloors",
          "pubProvidedIdSystem",
          "pubmaticBidAdapter",
          "pubxaiAnalyticsAdapter",
          "quantcastIdSystem",
          "richaudienceBidAdapter",
          "rtbhouseBidAdapter",
          "rtdModule",
          "rubiconBidAdapter",
          "schain",
          "sharedIdSystem",
          "sharethroughBidAdapter",
          "smilewantedBidAdapter",
          "sovrnBidAdapter",
          "sparteoBidAdapter",
          "themoneytizerBidAdapter",
          "topicsFpdModule",
          "unrulyBidAdapter",
          "userId",
          "videoheroesBidAdapter"
        ]
      }
    ],
    "toolMetadata": {
      "prebidInitStates": {
        "qpb": "complete",
        "tmzr": "complete"
      }
    },
    "url": "https://lebusmagique.fr"
  },
  {
    "libraries": [
      "googletag"
    ],
    "identitySolutions": [],
    "cdpPlatforms": [],
    "cmpInfo": {},
    "unknownAdTech": [],
    "date": "2025-07-12",
    "prebidInstances": [],
    "url": "https://pentaxuser.com"
  },
  {
    "libraries": [
      "apstag",
      "googletag"
    ],
    "identitySolutions": [
      "ID5"
    ],
    "cdpPlatforms": [],
    "cmpInfo": {
      "ccpaApplies": true,
      "uspString": "1---",
      "name": "OneTrust",
      "gdprApplies": false
    },
    "unknownAdTech": [],
    "date": "2025-07-12",
    "prebidInstances": [
      {
        "globalVarName": "mmPrebid",
        "version": "v9.41.0",
        "modules": [
          "MMBidAdapter",
          "acuityadsBidAdapter",
          "adyoulikeBidAdapter",
          "appnexusBidAdapter",
          "cadentApertureMXBidAdapter",
          "colossussspBidAdapter",
          "consentManagementGpp",
          "consentManagementTcf",
          "consentManagementUsp",
          "conversantBidAdapter",
          "criteoBidAdapter",
          "feedadBidAdapter",
          "fpdModule",
          "gptPreAuction",
          "gridBidAdapter",
          "gumgumBidAdapter",
          "improvedigitalBidAdapter",
          "insticatorBidAdapter",
          "ixBidAdapter",
          "kargoBidAdapter",
          "kueezRtbBidAdapter",
          "liveIntentIdSystem",
          "medianetBidAdapter",
          "minutemediaBidAdapter",
          "nativoBidAdapter",
          "nextMillenniumBidAdapter",
          "oguryBidAdapter",
          "onetagBidAdapter",
          "openxBidAdapter",
          "optidigitalBidAdapter",
          "paapi",
          "paapiForGpt",
          "pgamsspBidAdapter",
          "priceFloors",
          "pubProvidedIdSystem",
          "pubmaticBidAdapter",
          "richaudienceBidAdapter",
          "riseBidAdapter",
          "rubiconBidAdapter",
          "schain",
          "seedtagBidAdapter",
          "sharethroughBidAdapter",
          "smartadserverBidAdapter",
          "smilewantedBidAdapter",
          "sonobiBidAdapter",
          "sovrnBidAdapter",
          "teadsBidAdapter",
          "tripleliftBidAdapter",
          "ttdBidAdapter",
          "undertoneBidAdapter",
          "unifiedIdSystem",
          "unrulyBidAdapter",
          "userId",
          "viantOrtbBidAdapter",
          "vidazooBidAdapter",
          "yieldmoBidAdapter"
        ]
      }
    ],
    "toolMetadata": {
      "prebidInitStates": {
        "mmPrebid": "complete"
      }
    },
    "url": "https://bamsmackpow.com"
  }
]
